Workbook

Sheet Leia-me
A1: Medidor do Programa de Governo Lula 2027-2030: base de dados
A3: Origem | B3: PDF do programa de governo (84 páginas, 13 eixos) enviado pelo usuário, que informou ser o documento registrado no TSE. Extração em 25/10/2026.
A4: O que é | B4: Lista de compromissos futuros extraídos do texto. O programa não traz lista numerada; cada linha é um resumo, em palavras próprias, de um compromisso do texto. Há um item por compromisso, mas compromissos muito parecidos foram agrupados.
A5: Quantidade | B5: 289 itens (veja a aba Resumo para a divisão por eixo e tipo).
A6: Tipos | B6: Meta numérica: traz número ou prazo explícito. Marco verificável: criar, instituir, regulamentar, aprovar algo (feito ou não feito). Diretriz: 'fortalecer', 'ampliar', 'manter', sem meta; precisa de indicador antes de ser medida.
A7: Linha de base | B7: Números que o próprio programa cita como resultado do mandato atual. São afirmações do documento, não foram verificados de forma independente.
A8: Pág. | B8: Página aproximada (±1) no PDF; faixas como 15-16 indicam que o tema atravessa páginas.
A9: Início do acompanhamento | B9: Os compromissos valem para o mandato 2027-2030. Todos começam como 'Não iniciada' e 0%. Itens com marco já cumprido antes da posse (ex.: PEC enviada ao Congresso) estão anotados na coluna de linha de base.
A10: Classificação | B10: Eixo, tipo e resumo são interpretação de quem montou a base. Indicador e fonte sugeridos são pontos de partida e precisam ser validados antes da publicação.
A11: Como atualizar | B11: Edite apenas as colunas em azul na aba Propostas: Status (lista), % de avanço (0 a 100%), Atualizado em, Link da fonte, Observações. As demais colunas e a aba Resumo não precisam de edição.
A12: Regra sugerida de status | B12: Concluída = marco cumprido ou meta atingida (avanço 100%). Em andamento = ato ou ação iniciada, com fonte pública. Sem dados = não há fonte para medir. Cite sempre o link da fonte oficial.
A13: Exemplo de linha preenchida | B13: Status: Em andamento | % de avanço: 35% | Atualizado em: 15/03/2027 | Link: https://www.in.gov.br/... | Observações: decreto publicado, regulamentação pendente. (Exemplo ilustrativo, não está nos dados.)
A14: Neutralidade | B14: Para o site e o app, mostre sempre a fonte e a data de cada atualização, e deixe claro que o status é uma classificação do projeto, não um dado oficial do governo.
... A19: Itens fora do balanço | B19: Ficaram de fora do balanço o preâmbulo (itens 1 a 11 do PDF) e diretrizes só descritivas ou repetidas (ex.: 12, 48, 50, 52, 56, 61, 66, 68, 72, 73, 76, 82, 83, 90, 92, 93, 97, 98, 104, 105, 112, 114, 117, 121).

Sheet Propostas
A1: ID | B1: Eixo | C1: Tema | D1: Proposta (resumo) | E1: Pág. | F1: Tipo | G1: Meta | H1: Linha de base citada no programa | I1: Indicador / fonte sugerida | J1: Status | K1: % de avanço | L1: Atualizado em | M1: Link da fonte da atualização | N1: Observações
A2: P001 | B2: 1. Democracia e Estado | C2: Reforma política | D2: Reforma política e eleitoral para aproximar a representação política da sociedade | E2: 15 | F2: Marco verificável | I2: Câmara e Senado (tramitação de PEC/PL) | J2: Não iniciada | K2: 0
A3: P002 | B3: 1. Democracia e Estado | C3: Participação social | D3: Manter conselhos e conferências nacionais e o Sistema de Participação Social | E3: 15 | F3: Diretriz (sem meta) | H3: 28 conferências desde 2023 | I3: Secretaria-Geral da Presidência (nº de conferências) | J3: Não iniciada | K3: 0
A4: P003 | B4: 1. Democracia e Estado | C4: Participação social | D4: PPA 2028-2031 mais participativo e participação social no ciclo orçamentário | E4: 15 | F4: Marco verificável | G4: PPA 2028-2031 | H4: PPA atual: 1,4 mi de participantes | I4: Projeto de lei do PPA e plataforma Brasil Participativo | J4: Não iniciada | K4: 0
A5: P004 | B5: 1. Democracia e Estado | C5: Orçamento | D5: Debater com a sociedade o sistema de emendas parlamentares | E5: 15-16 | F5: Diretriz (sem meta) | H5: Emendas 2026: R$ 50 bi | I5: Lei Orçamentária (valor de emendas) | J5: Não iniciada | K5: 0
A6: P005 | B6: 1. Democracia e Estado | C6: Plataformas digitais | D6: Avançar na regulação democrática de redes sociais e plataformas | E6: 16 | F6: Marco verificável | I6: Projetos de lei e regulamentos publicados | J6: Não iniciada | K6: 0
A7: P006 | B7: 1. Democracia e Estado | C7: Justiça | D7: Diálogo permanente com o Judiciário para reduzir a morosidade | E7: 16 | F7: Diretriz (sem meta) | I7: A definir: indicador oficial do órgão responsável | J7: Não iniciada | K7: 0
A8: P007 | B8: 1. Democracia e Estado | C8: Servidores | D8: Aprofundar valorização de servidores pela Mesa Nacional de Negociação Permanente | E8: 16 | F8: Diretriz (sem meta) | H8: Mesa reaberta no mandato atual | I8: A definir: indicador oficial do órgão responsável | J8: Não iniciada | K8: 0
A9: P008 | B9: 1. Democracia e Estado | C9: Gestão | D9: "Governo para cada pessoa": serviços personalizados e Base de Dados do Brasil | E9: 16-17 | F9: Diretriz (sem meta) | I9: A definir: indicador oficial do órgão responsável | J9: Não iniciada | K9: 0
A10: P009 | B10: 1. Democracia e Estado | C10: Governo digital | D10: Universalizar serviços públicos digitais de qualidade e ampliar o Gov.br | E10: 17 | F10: Diretriz (sem meta) | H10: Gov.br: mais de 5 mil serviços | I10: Painel do Gov.br (nº de serviços) | J10: Não iniciada | K10: 0
A11: P010 | B11: 1. Democracia e Estado | C11: Letramento digital | D11: Instituir a Política Nacional de Letramento Digital | E11: 17 | F11: Marco verificável | I11: Diário Oficial da União / Congresso: publicação do ato (lei, decreto, portaria) | J11: Não iniciada | K11: 0
A12: P011 | B12: 1. Democracia e Estado | C12: Soberania digital | D12: Criar o Conselho Nacional pela Soberania Digital, com participação da sociedade | E12: 17 | F12: Marco verificável | I12: Diário Oficial da União / Congresso: publicação do ato (lei, decreto, portaria) | J12: Não iniciada | K12: 0
A13: P012 | B13: 1. Democracia e Estado | C13: Gestão | D13: Aprimorar centralização e compartilhamento de serviços de suporte entre ministérios | E13: 17 | F13: Diretriz (sem meta) | I13: A definir: indicador oficial do órgão responsável | J13: Não iniciada | K13: 0
A14: P013 | B14: 1. Democracia e Estado | C14: Compras públicas | D14: Aprimorar o uso do poder de compra do Estado (Contrata+ Brasil) | E14: 17 | F14: Diretriz (sem meta) | I14: A definir: indicador oficial do órgão responsável | J14: Não iniciada | K14: 0
A15: P014 | B15: 1. Democracia e Estado | C15: Patrimônio da União | D15: Continuar o Imóvel da Gente e o Fundo Imobiliário da União | E15: 17-18 | F15: Diretriz (sem meta) | H15: 1,8 mil imóveis destinados | I15: A definir: indicador oficial do órgão responsável | J15: Não iniciada | K15: 0
A16: P015 | B16: 1. Democracia e Estado | C16: Federalismo | D16: Fortalecer cooperação e governança federativa (infraestrutura digital, formação de servidores) | E16: 18 | F16: Diretriz (sem meta) | I16: A definir: indicador oficial do órgão responsável | J16: Não iniciada | K16: 0
A17: P016 | B17: 1. Democracia e Estado | C17: Integridade | D17: Aprofundar o Plano de Integridade e Combate à Corrupção 2025-2027 | E17: 18 | F17: Diretriz (sem meta) | I17: CGU | J17: Não iniciada | K17: 0
A18: P017 | B18: 1. Democracia e Estado | C18: Transparência | D18: Evoluir o Portal da Transparência para plataforma inteligente com dados abertos e IA | E18: 18 | F18: Marco verificável | I18: CGU | J18: Não iniciada | K18: 0
A19: P018 | B19: 1. Democracia e Estado | C19: Controle social | D19: Fortalecer a Ouvidoria-Geral da União e a participação no combate à corrupção | E19: 18 | F19: Diretriz (sem meta) | I19: CGU | J19: Não iniciada | K19: 0
A20: P019 | B20: 2. Desigualdades | C20: Proteção social | D20: Manter, aperfeiçoar e ampliar políticas de proteção social e de transferência de renda | E20: 18 | F20: Diretriz (sem meta) | I20: MDS (famílias atendidas, pobreza extrema) | J20: Não iniciada | K20: 0
A21: P020 | B21: 2. Desigualdades | C21: Igualdade racial | D21: Implementar as deliberações da V CONAPIR | E21: 19 | F21: Diretriz (sem meta) | I21: A definir: indicador oficial do órgão responsável | J21: Não iniciada | K21: 0
A22: P021 | B22: 2. Desigualdades | C22: Igualdade racial | D22: Avançar na regulamentação do Estatuto da Igualdade Racial | E22: 19 | F22: Marco verificável | I22: Diário Oficial da União / Congresso: publicação do ato (lei, decreto, portaria) | J22: Não iniciada | K22: 0
A23: P022 | B23: 2. Desigualdades | C23: Igualdade racial | D23: Manter política de cotas e fomentar participação negra no funcionalismo, inclusive em cargos superiores | E23: 19 | F23: Diretriz (sem meta) | I23: A definir: indicador oficial do órgão responsável | J23: Não iniciada | K23: 0
A24: P023 | B24: 2. Desigualdades | C24: Educação étnico-racial | D24: Acelerar a Política Nacional de Equidade e Educação Escolar Quilombola (PNEERQ) | E24: 20 | F24: Diretriz (sem meta) | I24: A definir: indicador oficial do órgão responsável | J24: Não iniciada | K24: 0
A25: P024 | B25: 2. Desigualdades | C25: Quilombolas | D25: Abrir novos campi quilombo dos Institutos Federais | E25: 20 | F25: Marco verificável | H25: 1º campus em Minas Nova | I25: Diário Oficial da União / Congresso: publicação do ato (lei, decreto, portaria) | J25: Não iniciada | K25: 0
A26: P025 | B26: 2. Desigualdades | C26: Quilombolas | D26: Seguir titulando territórios quilombolas e acelerar os procedimentos | E26: 20 | F26: Diretriz (sem meta) | H26: 65 titulações e 72 decretos desde 2023 | I26: Incra (nº de titulações) | J26: Não iniciada | K26: 0
A27: P026 | B27: 2. Desigualdades | C27: Povos indígenas | D27: Demarcação e desintrusão de terras indígenas sempre que necessário | E27: 20 | F27: Diretriz (sem meta) | H27: 20 terras homologadas; 9 desintrusões | I27: Funai / MPI | J27: Não iniciada | K27: 0
A28: P027 | B28: 2. Desigualdades | C28: Povos indígenas | D28: Educação escolar indígena com autonomia e interculturalidade | E28: 20 | F28: Diretriz (sem meta) | I28: A definir: indicador oficial do órgão responsável | J28: Não iniciada | K28: 0
A29: P028 | B29: 2. Desigualdades | C29: Povos indígenas | D29: Implantar plenamente a Universidade Indígena | E29: 20 | F29: Marco verificável | H29: Criada em 2026 | I29: Diário Oficial da União / Congresso: publicação do ato (lei, decreto, portaria) | J29: Não iniciada | K29: 0
A30: P029 | B30: 2. Desigualdades | C30: Povos indígenas | D30: Reverter impactos na terra Yanomami e manter saúde indígena diferenciada | E30: 20-21 | F30: Diretriz (sem meta) | H30: Garimpo reduzido em 99% | I30: Sesai / Funai | J30: Não iniciada | K30: 0
A31: P030 | B31: 2. Desigualdades | C31: Mulheres | D31: Dar sequência ao Pacto de Enfrentamento ao Feminicídio | E31: 21 | F31: Diretriz (sem meta) | I31: Ministério das Mulheres | J31: Não iniciada | K31: 0
A32: P031 | B32: 2. Desigualdades | C32: Mulheres | D32: Concluir as 30 Casas da Mulher Brasileira e os 15 Centros de Referência da Mulher Brasileira | E32: 21 | F32: Meta numérica | G32: 30 casas e 15 centros | I32: Ministério das Mulheres (unidades entregues) | J32: Não iniciada | K32: 0
A33: P032 | B33: 2. Desigualdades | C33: Mulheres | D33: Ampliar as Salas Lilás | E33: 21 | F33: Diretriz (sem meta) | I33: A definir: indicador oficial do órgão responsável | J33: Não iniciada | K33: 0
A34: P033 | B34: 2. Desigualdades | C34: Mulheres | D34: Adquirir e distribuir aos estados kits de monitoramento de agressores | E34: 21 | F34: Marco verificável | I34: Diário Oficial da União / Congresso: publicação do ato (lei, decreto, portaria) | J34: Não iniciada | K34: 0
A35: P034 | B35: 2. Desigualdades | C35: Mulheres | D35: Capacitar forças de segurança no atendimento a vítimas de violência | E35: 21 | F35: Diretriz (sem meta) | I35: A definir: indicador oficial do órgão responsável | J35: Não iniciada | K35: 0
A36: P035 | B36: 2. Desigualdades | C36: Mulheres | D36: Autonomia econômica: Lei da Igualdade Salarial, crédito Pronaf, Mulheres Mil, empreendedorismo e ciência | E36: 21-22 | F36: Diretriz (sem meta) | I36: A definir: indicador oficial do órgão responsável | J36: Não iniciada | K36: 0
A37: P036 | B37: 2. Desigualdades | C37: Pessoas idosas | D37: Apoiar municípios na expansão de Centros-Dia e equipamentos de envelhecimento ativo | E37: 22 | F37: Diretriz (sem meta) | I37: A definir: indicador oficial do órgão responsável | J37: Não iniciada | K37: 0
A38: P037 | B38: 2. Desigualdades | C38: Pessoas idosas | D38: Apoiar mais vagas públicas em ILPIs e melhorar a fiscalização | E38: 22 | F38: Diretriz (sem meta) | I38: A definir: indicador oficial do órgão responsável | J38: Não iniciada | K38: 0
A39: P038 | B39: 2. Desigualdades | C39: Pessoas idosas | D39: Dar escala ao PADI Brasil (atenção domiciliar ao idoso) em todo o território | E39: 22 | F39: Meta numérica | G39: Cobertura nacional | H39: 2.655 municípios | I39: Ministério da Saúde (municípios com PADI) | J39: Não iniciada | K39: 0
A40: P039 | B40: 2. Desigualdades | C40: Pessoas idosas | D40: Ampliar parcerias com o setor privado para qualificar e contratar pessoas 60+ | E40: 23 | F40: Diretriz (sem meta) | I40: A definir: indicador oficial do órgão responsável | J40: Não iniciada | K40: 0
A41: P040 | B41: 2. Desigualdades | C41: Pessoas idosas | D41: Letramento digital para idosos e prevenção a fraudes | E41: 23 | F41: Diretriz (sem meta) | I41: A definir: indicador oficial do órgão responsável | J41: Não iniciada | K41: 0
A42: P041 | B42: 2. Desigualdades | C42: Pessoas com deficiência | D42: Manter o Viver sem Limites; fiscalizar acessibilidade e cotas de contratação | E42: 23 | F42: Diretriz (sem meta) | I42: A definir: indicador oficial do órgão responsável | J42: Não iniciada | K42: 0
A43: P042 | B43: 2. Desigualdades | C43: Pessoas com deficiência | D43: Ampliar Centros Especializados em Reabilitação e Oficinas Ortopédicas | E43: 23 | F43: Diretriz (sem meta) | H43: 52 CERs e 17 oficinas apoiados | I43: Ministério da Saúde | J43: Não iniciada | K43: 0
A44: P043 | B44: 2. Desigualdades | C44: Pessoas com deficiência | D44: Apoiar educação inclusiva e educação bilíngue de surdos | E44: 23 | F44: Diretriz (sem meta) | I44: A definir: indicador oficial do órgão responsável | J44: Não iniciada | K44: 0
A45: P044 | B45: 2. Desigualdades | C45: LGBTQIAP+ | D45: Considerar gênero, identidade e orientação sexual na formulação de políticas | E45: 23 | F45: Diretriz (sem meta) | I45: A definir: indicador oficial do órgão responsável | J45: Não iniciada | K45: 0
A46: P045 | B46: 2. Desigualdades | C46: Crianças | D46: Enfrentar a pobreza infantil e garantir o direito ao brincar | E46: 24 | F46: Diretriz (sem meta) | I46: A definir: indicador oficial do órgão responsável | J46: Não iniciada | K46: 0
A47: P046 | B47: 2. Desigualdades | C47: Crianças | D47: Aprimorar o ECA Digital, regulamentar uso de telas por faixa etária e plataformas de jogos | E47: 24 | F47: Marco verificável | I47: Diário Oficial da União / Congresso: publicação do ato (lei, decreto, portaria) | J47: Não iniciada | K47: 0
A48: P047 | B48: 2. Desigualdades | C48: Crianças | D48: Manter combate prioritário à pedofilia com inteligência e agilidade na punição | E48: 24 | F48: Diretriz (sem meta) | I48: A definir: indicador oficial do órgão responsável | J48: Não iniciada | K48: 0
A49: P048 | B49: 2. Desigualdades | C49: Juventude | D49: Aprimorar o Pé-de-Meia | E49: 24 | F49: Diretriz (sem meta) | I49: A definir: indicador oficial do órgão responsável | J49: Não iniciada | K49: 0
A50: P049 | B50: 2. Desigualdades | C50: Juventude | D50: Manter cursinhos populares (CPop) e fortalecer a assistência estudantil | E50: 24 | F50: Diretriz (sem meta) | I50: A definir: indicador oficial do órgão responsável | J50: Não iniciada | K50: 0
A51: P050 | B51: 2. Desigualdades | C51: Juventude | D51: Política de aprendizagem para o trabalho, empreendedorismo e crédito à juventude rural | E51: 24-25 | F51: Diretriz (sem meta) | I51: A definir: indicador oficial do órgão responsável | J51: Não iniciada | K51: 0
A52: P051 | B52: 2. Desigualdades | C52: Juventude | D52: Aprimorar a política de saúde mental da juventude | E52: 25 | F52: Diretriz (sem meta) | I52: A definir: indicador oficial do órgão responsável | J52: Não iniciada | K52: 0
A53: P052 | B53: 2. Desigualdades | C53: Juventude | D53: Apoiar produção cultural das periferias e ampliar a participação juvenil nas decisões | E53: 25 | F53: Diretriz (sem meta) | I53: A definir: indicador oficial do órgão responsável | J53: Não iniciada | K53: 0
A54: P053 | B54: 2. Desigualdades | C54: Assistência social | D54: Fortalecer o SUAS e integrá-lo à agenda de desastres climáticos | E54: 25 | F54: Diretriz (sem meta) | I54: MDS | J54: Não iniciada | K54: 0
A55: P054 | B55: 2. Desigualdades | C55: Cuidados | D55: Fortalecer e dar escala à Política Nacional de Cuidados | E55: 25-26 | F55: Diretriz (sem meta) | I55: A definir: indicador oficial do órgão responsável | J55: Não iniciada | K55: 0
... A58: P057 | B58: 2. Desigualdades | C58: Cuidados | D58: Instituir programa de capacitação de cuidadores | E58: 26 | F58: Marco verificável | I58: Diário Oficial da União / Congresso: publicação do ato (lei, decreto, portaria) | J58: Não iniciada | K58: 0
A59: P058 | B59: 3. Segurança pública | C59: Federalismo | D59: PEC da Segurança Pública (revisar atribuições dos entes federados) | E59: 27 | F59: Marco verificável | H59: Enviada ao Congresso | I59: Câmara e Senado (tramitação) | J59: Não iniciada | K59: 0
A60: P059 | B60: 3. Segurança pública | C60: Estrutura | D60: Criar o Ministério da Segurança Pública, após aprovação da PEC | E60: 30 | F60: Marco verificável | I60: Diário Oficial da União / Congresso: publicação do ato (lei, decreto, portaria) | J60: Não iniciada | K60: 0
A61: P060 | B61: 3. Segurança pública | C61: Crime organizado | D61: Manter asfixia financeira, agilizar procedimentos jurídicos e barrar candidaturas ligadas ao crime | E61: 27 | F61: Diretriz (sem meta) | H61: R$ 35,8 bi de prejuízo ao crime desde 2023 | I61: Polícia Federal / MJSP | J61: Não iniciada | K61: 0
A62: P061 | B62: 3. Segurança pública | C62: Crime organizado | D62: Fortalecer o Programa Brasil Contra o Crime Organizado (R$ 10 bi do FIIS para estados e municípios) | E62: 27-28 | F62: Meta numérica | G62: R$ 10 bi | H62: Lançado em maio/2026 | I62: MJSP (valor repassado) | J62: Não iniciada | K62: 0
A63: P062 | B63: 3. Segurança pública | C63: Presença do Estado | D63: Urbanização de favelas e periferias e requalificação de espaços públicos | E63: 28 | F63: Diretriz (sem meta) | I63: A definir: indicador oficial do órgão responsável | J63: Não iniciada | K63: 0
A64: P063 | B64: 3. Segurança pública | C64: Inteligência | D64: Consolidar o Sistema de Inteligência de Segurança Pública; modernizar SINESP e Infoseg; ampliar FICCOs | E64: 28 | F64: Marco verificável | I64: Diário Oficial da União / Congresso: publicação do ato (lei, decreto, portaria) | J64: Não iniciada | K64: 0
A65: P064 | B65: 3. Segurança pública | C65: Armas | D65: Manter controle de armas e munições; melhorar rastreabilidade e fiscalização | E65: 28 | F65: Diretriz (sem meta) | I65: Polícia Federal / Exército | J65: Não iniciada | K65: 0
A66: P065 | B66: 3. Segurança pública | C66: Sistema prisional | D66: Cumprir as metas do Plano Pena Justa | E66: 28 | F66: Diretriz (sem meta) | I66: A definir: indicador oficial do órgão responsável | J66: Não iniciada | K66: 0
A67: P066 | B67: 3. Segurança pública | C67: Sistema prisional | D67: Instituir o Pacto Nacional de Execução Penal contra o Crime Organizado | E67: 28 | F67: Marco verificável | I67: Diário Oficial da União / Congresso: publicação do ato (lei, decreto, portaria) | J67: Não iniciada | K67: 0
A68: P067 | B68: 3. Segurança pública | C68: Sistema prisional | D68: Fortalecer o sistema penitenciário federal e criar protocolo nacional de transferência de presos de alta periculosidade | E68: 28 | F68: Marco verificável | I68: Diário Oficial da União / Congresso: publicação do ato (lei, decreto, portaria) | J68: Não iniciada | K68: 0
A69: P068 | B69: 3. Segurança pública | C69: Amazônia | D69: Consolidar as FICCOs como política de Estado e manter as Forças Armadas nas fronteiras | E69: 29 | F69: Diretriz (sem meta) | I69: A definir: indicador oficial do órgão responsável | J69: Não iniciada | K69: 0
A70: P069 | B70: 3. Segurança pública | C70: Amazônia | D70: Investir em radares, drones, sensores, satélites e centros integrados de comando e controle | E70: 29 | F70: Diretriz (sem meta) | I70: A definir: indicador oficial do órgão responsável | J70: Não iniciada | K70: 0
A71: P070 | B71: 3. Segurança pública | C71: Crimes patrimoniais | D71: Expandir o Celular Seguro | E71: 29 | F71: Diretriz (sem meta) | H71: Mais de 4 mi de usuários | I71: MJSP | J71: Não iniciada | K71: 0
A72: P071 | B72: 3. Segurança pública | C72: Crimes digitais | D72: Reforçar prevenção e repressão a crimes financeiros e cibernéticos | E72: 29 | F72: Diretriz (sem meta) | I72: A definir: indicador oficial do órgão responsável | J72: Não iniciada | K72: 0
A73: P072 | B73: 3. Segurança pública | C73: Prevenção | D73: Prevenção da violência com foco na juventude negra; mediação comunitária e justiça restaurativa | E73: 29 | F73: Diretriz (sem meta) | I73: A definir: indicador oficial do órgão responsável | J73: Não iniciada | K73: 0
A74: P073 | B74: 3. Segurança pública | C74: Migração | D74: Implementar plenamente a Política Nacional de Migrações, Refúgio e Apatridia | E74: 30 | F74: Diretriz (sem meta) | I74: A definir: indicador oficial do órgão responsável | J74: Não iniciada | K74: 0
A75: P074 | B75: 3. Segurança pública | C75: Polícia | D75: Policiamento de proximidade, mais câmeras corporais com padrão nacional e controle da atividade policial | E75: 30 | F75: Diretriz (sem meta) | I75: A definir: indicador oficial do órgão responsável | J75: Não iniciada | K75: 0
A76: P075 | B76: 4. Educação | C76: Planejamento | D76: Cumprir as metas do Plano Nacional de Educação 2026-2036 | E76: 31 | F76: Diretriz (sem meta) | I76: Inep (monitoramento do PNE) | J76: Não iniciada | K76: 0
A77: P076 | B77: 4. Educação | C77: Alfabetização | D77: Alcançar 80% das crianças alfabetizadas na idade certa | E77: 31 | F77: Meta numérica | G77: 80% | H77: 66% em 2025 (meta era 64%) | I77: Inep / MEC (indicador Criança Alfabetizada) | J77: Não iniciada | K77: 0
A78: P077 | B78: 4. Educação | C78: Alfabetização | D78: Enfrentar o analfabetismo da população adulta | E78: 31 | F78: Diretriz (sem meta) | I78: IBGE (PNAD) | J78: Não iniciada | K78: 0
A79: P078 | B79: 4. Educação | C79: Aprendizagem | D79: Instituir estratégia nacional permanente de recomposição e aceleração das aprendizagens | E79: 31 | F79: Marco verificável | I79: Diário Oficial da União / Congresso: publicação do ato (lei, decreto, portaria) | J79: Não iniciada | K79: 0
A80: P079 | B80: 4. Educação | C80: Creches | D80: Nova edição do Novo PAC: ampliar fomento a creches e pré-escolas | E80: 31 | F80: Diretriz (sem meta) | H80: 3.562 unidades em 2.360 municípios | I80: Painel do Novo PAC | J80: Não iniciada | K80: 0
A81: P080 | B81: 4. Educação | C81: Tempo integral | D81: Prioridade absoluta à expansão da educação em tempo integral (financiamento via Fundeb) | E81: 31 | F81: Diretriz (sem meta) | H81: 1,8 mi de matrículas novas em 2023-2025 | I81: Censo Escolar (Inep) | J81: Não iniciada | K81: 0
A82: P081 | B82: 4. Educação | C82: Infraestrutura escolar | D82: Manter apoio a estados e municípios na construção de escolas | E82: 32 | F82: Diretriz (sem meta) | H82: 686 escolas de tempo integral | I82: Painel do Novo PAC | J82: Não iniciada | K82: 0
A83: P082 | B83: 4. Educação | C83: Conectividade | D83: Universalizar internet de qualidade nas escolas | E83: 32 | F83: Meta numérica | G83: 100% das escolas | H83: 75% das escolas | I83: MEC / Anatel | J83: Não iniciada | K83: 0
A84: P083 | B84: 4. Educação | C84: Permanência | D84: Dar continuidade e fortalecer o Pé-de-Meia | E84: 32 | F84: Diretriz (sem meta) | H84: 7,3 mi de jovens beneficiados | I84: MEC | J84: Não iniciada | K84: 0
A85: P084 | B85: 4. Educação | C85: Acesso digital | D85: Ampliar o acervo do MEC Livros e as línguas do MEC Idiomas | E85: 32 | F85: Diretriz (sem meta) | I85: A definir: indicador oficial do órgão responsável | J85: Não iniciada | K85: 0
A86: P085 | B86: 4. Educação | C86: Gestão | D86: Apoio técnico a estados e municípios e compartilhamento de dados educacionais | E86: 32 | F86: Diretriz (sem meta) | I86: A definir: indicador oficial do órgão responsável | J86: Não iniciada | K86: 0
A87: P086 | B87: 4. Educação | C87: Professores | D87: Manter o Piso Nacional do Magistério | E87: 32-33 | F87: Diretriz (sem meta) | I87: MEC | J87: Não iniciada | K87: 0
A88: P087 | B88: 4. Educação | C88: Professores | D88: Continuar Pé-de-Meia Licenciatura e Bolsa Mais Professores | E88: 33 | F88: Diretriz (sem meta) | I88: A definir: indicador oficial do órgão responsável | J88: Não iniciada | K88: 0
A89: P088 | B89: 4. Educação | C89: Educação profissional | D89: Expandir a rede de Institutos Federais (+111 campi em 106 municípios) | E89: 33 | F89: Meta numérica | G89: 111 campi | H89: Em andamento | I89: MEC / Setec | J89: Não iniciada | K89: 0
A90: P089 | B90: 4. Educação | C90: Ensino superior | D90: Concluir obras em curso, inclusive de novos campi | E90: 33 | F90: Diretriz (sem meta) | H90: 10 campi e 367 obras no Novo PAC | I90: Painel do Novo PAC | J90: Não iniciada | K90: 0
A91: P090 | B91: 4. Educação | C91: Ensino superior | D91: Concluir a nova unidade do ITA no Ceará | E91: 33 | F91: Marco verificável | I91: Diário Oficial da União / Congresso: publicação do ato (lei, decreto, portaria) | J91: Não iniciada | K91: 0
A92: P091 | B92: 4. Educação | C92: Ensino superior | D92: Concluir a implantação da Universidade Indígena e da Universidade do Esporte | E92: 33 | F92: Marco verificável | I92: Diário Oficial da União / Congresso: publicação do ato (lei, decreto, portaria) | J92: Não iniciada | K92: 0
A93: P092 | B93: 4. Educação | C93: Ensino superior | D93: Novo ciclo de expansão e interiorização da educação superior pública | E93: 33 | F93: Marco verificável | I93: Diário Oficial da União / Congresso: publicação do ato (lei, decreto, portaria) | J93: Não iniciada | K93: 0
A94: P093 | B94: 4. Educação | C94: Ensino superior | D94: Aperfeiçoar a assistência estudantil | E94: 33 | F94: Diretriz (sem meta) | I94: A definir: indicador oficial do órgão responsável | J94: Não iniciada | K94: 0
A95: P094 | B95: 4. Educação | C95: Pós-graduação | D95: Ampliar e melhorar a pós-graduação em regiões pouco atendidas | E95: 34 | F95: Diretriz (sem meta) | I95: Capes | J95: Não iniciada | K95: 0
A96: P095 | B96: 4. Educação | C96: Hospitais universitários | D96: Implantar novos hospitais universitários articulados ao Agora Tem Especialistas | E96: 34 | F96: Diretriz (sem meta) | H96: 13 novas unidades | I96: A definir: indicador oficial do órgão responsável | J96: Não iniciada | K96: 0
A97: P096 | B97: 5. Saúde | C97: Atenção básica | D97: Apoiar expansão e qualificação das equipes de saúde da família e multiprofissionais | E97: 34-35 | F97: Diretriz (sem meta) | I97: Ministério da Saúde (e-Gestor) | J97: Não iniciada | K97: 0
A98: P097 | B98: 5. Saúde | C98: Saúde digital | D98: Intensificar teleconsultas, teleorientação e teleacolhimento | E98: 35 | F98: Diretriz (sem meta) | H98: 5.257 kits entregues | I98: A definir: indicador oficial do órgão responsável | J98: Não iniciada | K98: 0
A99: P098 | B99: 5. Saúde | C99: Diagnóstico | D99: Ampliar oferta de exames na atenção básica | E99: 35 | F99: Diretriz (sem meta) | I99: A definir: indicador oficial do órgão responsável | J99: Não iniciada | K99: 0
A100: P099 | B100: 5. Saúde | C100: Integração | D100: Integrar atenção primária, vigilância, assistência farmacêutica e especializada (OCI) | E100: 35 | F100: Diretriz (sem meta) | I100: A definir: indicador oficial do órgão responsável | J100: Não iniciada | K100: 0
A101: P100 | B101: 5. Saúde | C101: Prontuário | D101: Consolidar o prontuário único do cidadão (RNDS), com agendamento e exames no celular | E101: 35 | F101: Marco verificável | I101: Diário Oficial da União / Congresso: publicação do ato (lei, decreto, portaria) | J101: Não iniciada | K101: 0
A102: P101 | B102: 5. Saúde | C102: Inteligência artificial | D102: Usar IA em triagem, priorização de casos graves e regulação por risco clínico | E102: 35 | F102: Diretriz (sem meta) | I102: A definir: indicador oficial do órgão responsável | J102: Não iniciada | K102: 0
...

Sheet Lula 2022 (2023-2026)
A1: ID | B1: Diretriz nº (PDF 2022) | C1: Pág. (PDF 2022) | D1: Eixo (mesmos 13 de 2027) | E1: Tema | F1: Compromisso de 2022 (resumo) | G1: Tipo | H1: Status | I1: Evidência | J1: Fonte (nome) | K1: Classe da fonte | L1: Link da fonte | M1: Data do fato ou da fonte | N1: Consultado em
A2: H099 | B2: 99 | C2: 17 | D2: 1. Democracia e Estado | E2: Direitos civis | F2: Defender direitos civis, liberdade religiosa e combater a intolerância | G2: Diretriz (sem meta) | H2: Sem dados | I2: Ainda sem pesquisa de fonte; entra na próxima rodada. | N2: 26/10/2026
A3: H106 | B3: 106 | C3: 18 | D3: 1. Democracia e Estado | E3: Participação social | F3: Retomar o diálogo com movimentos sociais e sociedade civil | G3: Diretriz (sem meta) | H3: Sem dados | I3: Ainda sem pesquisa de fonte; entra na próxima rodada. | N3: 26/10/2026
A4: H107 | B4: 107 | C4: 18 | D4: 1. Democracia e Estado | E4: Reforma política | F4: Reforma política que fortaleça a democracia representativa e participativa | G4: Marco verificável | H4: Sem dados | I4: Pesquisado nesta rodada sem fonte consolidada. | N4: 26/10/2026
A5: H108 | B5: 108 | C5: 19 | D5: 1. Democracia e Estado | E5: Participação social | F5: Restaurar as instâncias de participação social extintas | G5: Marco verificável | H5: Concluída | I5: Decreto 11.406/2023 instituiu o Conselho de Participação Social; o Decreto 11.407/2023 instituiu o Sistema de Participação Social. | J5: Planalto - Decreto 11.406 | K5: Oficial | L5: https://www.planalto.gov.br/ccivil_03/_ato2023-2026/2023/decreto/D11406.htm | M5: 31/01/2023 | N5: 26/10/2026
A6: H109 | B6: 109 | C6: 19 | D6: 1. Democracia e Estado | E6: Participação social | F6: Criar novas instâncias de participação direta, inclusive no orçamento federal | G6: Marco verificável | H6: Sem dados | I6: Ainda sem pesquisa de fonte; entra na próxima rodada. | N6: 26/10/2026
A7: H110 | B7: 110 | C7: 19 | D7: 1. Democracia e Estado | E7: Federalismo | F7: Fortalecer o federalismo e o apoio a estados e municípios | G7: Diretriz (sem meta) | H7: Sem dados | I7: Ainda sem pesquisa de fonte; entra na próxima rodada. | N7: 26/10/2026
A8: H111 | B8: 111 | C8: 19 | D8: 1. Democracia e Estado | E8: Integridade | F8: Política de prevenção e combate à corrupção e de transparência | G8: Diretriz (sem meta) | H8: Sem dados | I8: Ainda sem pesquisa de fonte; entra na próxima rodada. | N8: 26/10/2026
A9: H113 | B9: 113 | C9: 19 | D9: 1. Democracia e Estado | E9: Transparência | F9: Reabrir o governo e garantir o cumprimento da Lei de Acesso à Informação | G9: Diretriz (sem meta) | H9: Sem dados | I9: Ainda sem pesquisa de fonte; entra na próxima rodada. | N9: 26/10/2026
A10: H115 | B10: 115 | C10: 20 | D10: 1. Democracia e Estado | E10: Estado | F10: Reforma do Estado com mais transparência nos processos decisórios | G10: Diretriz (sem meta) | H10: Sem dados | I10: Ainda sem pesquisa de fonte; entra na próxima rodada. | N10: 26/10/2026
A11: H116 | B11: 116 | C11: 20 | D11: 1. Democracia e Estado | E11: Servidores | F11: Retomar a valorização dos servidores públicos | G11: Diretriz (sem meta) | H11: Sem dados | I11: Ainda sem pesquisa de fonte; entra na próxima rodada. | N11: 26/10/2026
A12: H118 | B12: 118 | C12: 20 | D12: 1. Democracia e Estado | E12: Comunicação | F12: Regulamentar mecanismos de pluralidade e democratização da comunicação | G12: Marco verificável | H12: Sem dados | I12: Ainda sem pesquisa de fonte; entra na próxima rodada. | N12: 26/10/2026
A13: H119 | B13: 119 | C13: 20 | D13: 1. Democracia e Estado | E13: Plataformas digitais | F13: Fortalecer a legislação sobre plataformas digitais | G13: Diretriz (sem meta) | H13: Em andamento | I13: STF reinterpretou o art. 19 do Marco Civil da Internet em 2025; não localizei lei específica de regulação aprovada. | J13: Migalhas (artigo) | K13: Imprensa | L13: https://www.migalhas.com.br/depeso/444149/stf-publica-acordao-com-releitura-do-art-19-do-marco-civil-da-internet | M13: s/d | N13: 26/10/2026
A14: H120 | B14: 120 | C14: 20 | D14: 1. Democracia e Estado | E14: Imprensa | F14: Garantir segurança do jornalismo e punir a violência contra jornalistas | G14: Diretriz (sem meta) | H14: Sem dados | I14: Ainda sem pesquisa de fonte; entra na próxima rodada. | N14: 26/10/2026
A15: H019 | B15: 19 | C15: 5 | D15: 2. Desigualdades | E15: Assistência social | F15: Reconstruir e fortalecer o SUAS e a inclusão produtiva | G15: Diretriz (sem meta) | H15: Sem dados | I15: Ainda sem pesquisa de fonte; entra na próxima rodada. | N15: 26/10/2026
A16: H020 | B16: 20 | C16: 5 | D16: 2. Desigualdades | E16: Assistência social | F16: Bolsa Família renovado e ampliado | G16: Marco verificável | H16: Concluída | I16: Lei 14.601/2023 instituiu o novo Programa Bolsa Família. | J16: Senado Federal - Legislação | K16: Oficial | L16: https://legis.senado.leg.br/norma/37200398/publicacao/37206268 | M16: 19/06/2023 | N16: 26/10/2026
A17: H036 | B17: 36 | C17: 8 | D17: 2. Desigualdades | E17: Mulheres | F17: Salários iguais para trabalhos iguais | G17: Marco verificável | H17: Concluída | I17: Lei 14.611/2023 dispõe sobre igualdade salarial e de critérios remuneratórios entre mulheres e homens. | J17: Senado Federal - Legislação | K17: Oficial | L17: https://legis.senado.leg.br/norma/37349718/publicacao/37350224 | M17: 03/07/2023 | N17: 26/10/2026
A18: H037 | B18: 37 | C18: 8 | D18: 2. Desigualdades | E18: Mulheres | F18: Combater a violência contra a mulher e a impunidade de feminicídios | G18: Diretriz (sem meta) | H18: Em andamento | I18: Lei 14.994/2024 (pacote antifeminicídio) endureceu penas; reportagem registra as primeiras condenações. Sem fonte oficial localizada. | J18: Jovem Pan (coluna) | K18: Imprensa | L18: https://jovempan.com.br/colunistas/bruno-pinheiro/pacote-antifeminicidio-completa-um-ano-com-primeiras-condenacoes-e-penas-mais-duras-em-todo-o-pais/ | M18: s/d | N18: 26/10/2026
A19: H038 | B19: 38 | C19: 8 | D19: 2. Desigualdades | E19: Igualdade racial | F19: Políticas de promoção da igualdade racial e combate ao racismo estrutural | G19: Diretriz (sem meta) | H19: Em andamento | I19: Lei 14.600/2023 reorganizou os ministérios e consolidou a estrutura da área; resultados das políticas ainda não aferidos. | J19: Senado Federal - Legislação | K19: Oficial | L19: https://legis.senado.leg.br/norma/37200471 | M19: 19/06/2023 | N19: 26/10/2026
A20: H039 | B20: 39 | C20: 8 | D20: 2. Desigualdades | E20: Igualdade racial | F20: Continuidade e ampliação das cotas sociais e raciais | G20: Marco verificável | H20: Concluída | I20: Lei 14.723/2023 atualizou a Lei de Cotas no ensino federal. | J20: Agência Senado | K20: Oficial | L20: https://www12.senado.leg.br/noticias/materias/2023/11/14/sancionada-ampliacao-da-lei-de-cotas | M20: 14/11/2023 | N20: 26/10/2026
A21: H040 | B21: 40 | C21: 8 | D21: 2. Desigualdades | E21: Povos indígenas | F21: Assegurar a posse das terras indígenas | G21: Diretriz (sem meta) | H21: Em andamento | I21: Homologações retomadas no mandato (ex.: três terras no Ceará em ago/2025); processo de demarcação segue em curso. | J21: Agência Brasil (EBC) | K21: Agência pública | L21: https://agenciabrasil.ebc.com.br/direitos-humanos/noticia/2025-08/lula-homologa-tres-novas-terras-indigenas-no-ceara | M21: 08/2025 | N21: 26/10/2026
A22: H041 | B22: 41 | C22: 9 | D22: 2. Desigualdades | E22: LGBTQIA+ | F22: Políticas de direitos, combate à discriminação e saúde integral da população LGBTQIA+ | G22: Diretriz (sem meta) | H22: Sem dados | I22: Ainda sem pesquisa de fonte; entra na próxima rodada. | N22: 26/10/2026
A23: H042 | B23: 42 | C23: 9 | D23: 2. Desigualdades | E23: Juventude | F23: Oportunidades à juventude, com acesso à educação e permanência | G23: Diretriz (sem meta) | H23: Em andamento | I23: Lei 14.818/2024 instituiu o incentivo financeiro-educacional Pé-de-Meia; execução em curso. | J23: Senado Federal - Legislação | K23: Oficial | L23: https://legis.senado.leg.br/norma/38165461 | M23: 16/01/2024 | N23: 26/10/2026
A24: H043 | B24: 43 | C24: 9 | D24: 2. Desigualdades | E24: Pessoas com deficiência | F24: Brasil inclusivo e acessível, com acesso a saúde, educação e trabalho | G24: Diretriz (sem meta) | H24: Em andamento | I24: Decreto 11.793/2023 instituiu o Plano Novo Viver sem Limite; execução em curso. | J24: Senado Federal - Legislação | K24: Oficial | L24: https://legis.senado.leg.br/norma/37855201 | M24: 23/11/2023 | N24: 26/10/2026
A25: H044 | B25: 44 | C25: 9 | D25: 2. Desigualdades | E25: Infância | F25: Prioridade absoluta à criança e ao adolescente, com combate ao trabalho infantil | G25: Diretriz (sem meta) | H25: Sem dados | I25: Ainda sem pesquisa de fonte; entra na próxima rodada. | N25: 26/10/2026
A26: H045 | B26: 45 | C26: 10 | D26: 2. Desigualdades | E26: Idosos | F26: Rede de cuidados e políticas para o envelhecimento ativo | G26: Diretriz (sem meta) | H26: Em andamento | I26: Lei 15.069/2024 instituiu a Política Nacional de Cuidados; implementação em curso. | J26: Senado Federal - Legislação | K26: Oficial | L26: https://legis.senado.leg.br/norma/39993021/publicacao/40009222 | M26: 23/12/2024 | N26: 26/10/2026
A27: H046 | B27: 46 | C27: 10 | D27: 2. Desigualdades | E27: Animais | F27: Proteção e garantia dos direitos dos animais | G27: Diretriz (sem meta) | H27: Sem dados | I27: Ainda sem pesquisa de fonte; entra na próxima rodada. | N27: 26/10/2026
A28: H031 | B28: 31 | C28: 7 | D28: 3. Segurança pública | E28: Segurança | F28: Política nacional integrada para reduzir homicídios e enfrentar o crime organizado e as milícias | G28: Diretriz (sem meta) | H28: Sem dados | I28: Ainda sem pesquisa de fonte; entra na próxima rodada. | N28: 26/10/2026
A29: H032 | B29: 32 | C29: 7 | D29: 3. Segurança pública | E29: Segurança | F29: Aprimorar o Sistema Único de Segurança Pública e reformar as instituições | G29: Diretriz (sem meta) | H29: Em andamento | I29: PEC 18/2025 aprovada na Câmara (mar/2026); CCJ do Senado concluiu a análise em 14/10/2026 e o plenário tinha votação marcada para 15/10. Resultado não confirmado nesta rodada. | J29: DGABC (notícia) | K29: Imprensa | L29: https://www.dgabc.com.br/Noticia/4352814/alcolumbre-anuncia-votacao-da-pec-da-seguranca-publica-para-esta-quinta-feira | M29: 15/10/2026 | N29: 26/10/2026
A30: H033 | B30: 33 | C30: 7 | D30: 3. Segurança pública | E30: Segurança | F30: Valorizar o profissional de segurança pública | G30: Diretriz (sem meta) | H30: Sem dados | I30: Ainda sem pesquisa de fonte; entra na próxima rodada. | N30: 26/10/2026
A31: H034 | B31: 34 | C31: 7 | D31: 3. Segurança pública | E31: Drogas | F31: Nova política sobre drogas focada em redução de riscos | G31: Diretriz (sem meta) | H31: Sem dados | I31: Pesquisado nesta rodada sem fonte consolidada. | N31: 26/10/2026
A32: H035 | B32: 35 | C32: 8 | D32: 3. Segurança pública | E32: Segurança | F32: Melhorar a qualificação técnica dos policiais | G32: Diretriz (sem meta) | H32: Sem dados | I32: Ainda sem pesquisa de fonte; entra na próxima rodada. | N32: 26/10/2026
A33: H021 | B33: 21 | C33: 5 | D33: 4. Educação | E33: Plano Nacional de Educação | F33: Retomar as metas do Plano Nacional de Educação | G33: Marco verificável | H33: Em andamento | I33: Novo PNE sancionado como Lei 15.388, de 14/04/2026 (PL 2614/2024); o cumprimento das metas ainda precisa ser aferido. | J33: Congresso Nacional - PL 2614/2024 | K33: Oficial | L33: https://www.congressonacional.leg.br/web/atividade/materias/-/materia/172100 | M33: 14/04/2026 | N33: 26/10/2026
A34: H022 | B34: 22 | C34: 5 | D34: 4. Educação | E34: Educação básica | F34: Fortalecer a educação pública universal e de qualidade | G34: Diretriz (sem meta) | H34: Em andamento | I34: Lei 14.640/2023 instituiu o Programa Escola em Tempo Integral; execução em curso. | J34: Senado Federal - Legislação | K34: Oficial | L34: https://legis.senado.leg.br/norma/37435287 | M34: 31/07/2023 | N34: 26/10/2026
A35: H023 | B35: 23 | C35: 6 | D35: 5. Saúde | E35: SUS | F35: Dar condições ao SUS para retomar atendimento, tratar sequelas da covid-19 e retomar a vacinação | G35: Diretriz (sem meta) | H35: Sem dados | I35: Ainda sem pesquisa de fonte; entra na próxima rodada. | N35: 26/10/2026
A36: H024 | B36: 24 | C36: 6 | D36: 5. Saúde | E36: Saúde | F36: Retomar o Mais Médicos | G36: Marco verificável | H36: Concluída | I36: Lei 14.621/2023 reestruturou o programa. | J36: Senado Federal - Legislação | K36: Oficial | L36: https://legis.senado.leg.br/norma/37393603 | M36: 14/07/2023 | N36: 26/10/2026
A37: H024b | B37: 24b | C37: 6 | D37: 5. Saúde | E37: Saúde | F37: Retomar o Farmácia Popular | G37: Marco verificável | H37: Concluída | I37: Em fev/2025 todos os medicamentos do programa passaram a ser gratuitos. | J37: Conselho Federal de Farmácia (notícia) | K37: Imprensa | L37: https://site.cff.org.br/noticia/Noticias-gerais/13/02/2025/saude-anuncia-que-todos-os-medicamentos-do-farmacia-popular-agora-sao-gratuitos | M37: 13/02/2025 | N37: 26/10/2026
A38: H025 | B38: 25 | C38: 6 | D38: 6. Cultura e esporte | E38: Cultura | F38: Fortalecer as instituições culturais e recompor o financiamento da cultura | G38: Diretriz (sem meta) | H38: Em andamento | I38: Lei 14.600/2023 reorganizou os ministérios, com a estrutura federal da cultura; recomposição do financiamento ainda não aferida. | J38: Senado Federal - Legislação | K38: Oficial | L38: https://legis.senado.leg.br/norma/37200471 | M38: 19/06/2023 | N38: 26/10/2026
A39: H026 | B39: 26 | C39: 6 | D39: 6. Cultura e esporte | E39: Cultura | F39: Implantar o Sistema Nacional de Cultura | G39: Marco verificável | H39: Concluída | I39: Lei 14.835/2024 instituiu o marco regulatório do SNC. | J39: Senado Federal - Legislação | K39: Oficial | L39: https://legis.senado.leg.br/norma/38299941/publicacao/38300150 | M39: 04/04/2024 | N39: 26/10/2026
A40: H027 | B40: 27 | C40: 6 | D40: 6. Cultura e esporte | E40: Esporte | F40: Políticas universais de acesso ao esporte e ao lazer | G40: Diretriz (sem meta) | H40: Sem dados | I40: Ainda sem pesquisa de fonte; entra na próxima rodada. | N40: 26/10/2026
A41: H028 | B41: 28 | C41: 7 | D41: 6. Cultura e esporte | E41: Esporte | F41: Fortalecer a gestão do Sistema Nacional de Esportes | G41: Diretriz (sem meta) | H41: Sem dados | I41: Ainda sem pesquisa de fonte; entra na próxima rodada. | N41: 26/10/2026
A42: H086 | B42: 86 | C42: 15 | D42: 6. Cultura e esporte | E42: Turismo | F42: Estimular a indústria do turismo e retomar investimentos em infraestrutura turística | G42: Diretriz (sem meta) | H42: Sem dados | I42: Ainda sem pesquisa de fonte; entra na próxima rodada. | N42: 26/10/2026
A43: H029 | B43: 29 | C43: 7 | D43: 7. Direito à cidade | E43: Cidades | F43: Retomar o direito à cidade, com reforma urbana e transporte público | G43: Diretriz (sem meta) | H43: Sem dados | I43: Ainda sem pesquisa de fonte; entra na próxima rodada. | N43: 26/10/2026
A44: H030 | B44: 30 | C44: 7 | D44: 7. Direito à cidade | E44: Moradia | F44: Amplo programa de acesso à moradia | G44: Marco verificável | H44: Concluída | I44: Lei 14.620/2023 relançou o Minha Casa, Minha Vida; imprensa registra 2 milhões de moradias contratadas, antecipando a meta de 2026. | J44: Senado Federal - Legislação (lei) | K44: Oficial | L44: https://legis.senado.leg.br/norma/37377355 | M44: 13/07/2023 | N44: 26/10/2026
A45: H074 | B45: 74 | C45: 14 | D45: 7. Direito à cidade | E45: Saneamento | F45: Universalizar o saneamento básico e garantir a atuação das empresas estatais | G45: Diretriz (sem meta) | H45: Em andamento | I45: Novos decretos do marco legal do saneamento foram editados em jul/2023 (Decreto 11.599); a universalização depende de contratos em curso. | J45: Câmara dos Deputados - Legislação | K45: Oficial | L45: https://www2.camara.leg.br/legin/fed/decret/2023/decreto-11599-12-julho-2023-794435-norma-pe.html | M45: 12/07/2023 | N45: 26/10/2026
A46: H047 | B46: 47 | C46: 10 | D46: 8. Economia | E46: Crescimento | F46: Retomar o crescimento, o emprego e a renda com estabilidade de preços | G46: Diretriz (sem meta) | H46: Sem dados | I46: Ainda sem pesquisa de fonte; entra na próxima rodada. | N46: 26/10/2026
A47: H051 | B47: 51 | C47: 10 | D47: 8. Economia | E47: Fiscal | F47: Revogar o teto de gastos e criar um novo regime fiscal | G47: Marco verificável | H47: Concluída | I47: Lei Complementar 200/2023 instituiu o regime fiscal sustentável (arcabouço fiscal). | J47: Senado Federal - Legislação | K47: Oficial | L47: https://legis.senado.leg.br/norma/37553820/publicacao/37556723 | M47: 30/08/2023 | N47: 26/10/2026
A48: H053 | B48: 53 | C48: 11 | D48: 8. Economia | E48: Tributos | F48: Reforma tributária solidária, justa e sustentável | G48: Marco verificável | H48: Concluída | I48: EC 132/2023 promulgada em 20/12/2023; a regulamentação por leis complementares segue e a transição está prevista de 2029 a 2077. | J48: Agência Câmara | K48: Oficial | L48: https://www.camara.leg.br/noticias/1028787-apos-decadas-de-negociacao-o-congresso-aprovou-a-reforma-tributaria-em-2023/ | M48: 20/12/2023 | N48: 26/10/2026
A49: H054 | B49: 54 | C49: 11 | D49: 8. Economia | E49: Tributos | F49: Fazer os muito ricos pagarem imposto de renda | G49: Marco verificável | H49: Concluída | I49: Lei 15.270/2025 ampliou a isenção do IR e criou tributação mínima para altas rendas. | J49: Senado Federal - Legislação | K49: Oficial | L49: https://legis.senado.leg.br/norma/41758136/publicacao/41762089 | M49: 26/11/2025 | N49: 26/10/2026
A50: H055 | B50: 55 | C50: 11 | D50: 8. Economia | E50: Inflação | F50: Combater a inflação e a carestia de alimentos, combustíveis e eletricidade | G50: Diretriz (sem meta) | H50: Sem dados | I50: Ainda sem pesquisa de fonte; entra na próxima rodada. | N50: 26/10/2026
A51: H059 | B51: 59 | C51: 11 | D51: 8. Economia | E51: Câmbio | F51: Reduzir a volatilidade da moeda por meio da política cambial | G51: Diretriz (sem meta) | H51: Sem dados | I51: Ainda sem pesquisa de fonte; entra na próxima rodada. | N51: 26/10/2026
A52: H060 | B52: 60 | C52: 12 | D52: 8. Economia | E52: Crédito e dívidas | F52: Renegociar dívidas das famílias por bancos públicos | G52: Marco verificável | H52: Concluída | I52: Desenrola Brasil renegociou R$ 34 bilhões em dívidas até jan/2024. | J52: Agência Gov (EBC) | K52: Agência pública | L52: https://agenciagov.ebc.com.br/noticias/202401/desenrola-brasil-chega-a-r-34-bilhoes-em-dividas-renegociadas | M52: 01/2024 | N52: 26/10/2026
A53: H062 | B53: 62 | C53: 12 | D53: 8. Economia | E53: Indústria | F53: Reindustrialização do país | G53: Diretriz (sem meta) | H53: Em andamento | I53: Política Nova Indústria Brasil em execução; BNDES prevê R$ 140 bilhões até dez/2026. | J53: Diário do Transporte (notícia) | K53: Imprensa | L53: https://diariodotransporte.com.br/2026/06/22/nova-industria-incluindo-onibus-eletricos-e-minerais-criticos-para-baterias-tera-r-140-bilhoes-ate-dezembro-de-2026/ | M53: 22/06/2026 | N53: 26/10/2026
A54: H063 | B54: 63 | C54: 12 | D54: 8. Economia | E54: Indústria | F54: Política industrial voltada à transição tecnológica, ambiental e social | G54: Diretriz (sem meta) | H54: Em andamento | I54: Lei 14.902/2024 instituiu o programa Mover (mobilidade verde e inovação); execução em curso. | J54: Senado Federal - Legislação | K54: Oficial | L54: https://legis.senado.leg.br/norma/38654015 | M54: 27/06/2024 | N54: 26/10/2026
A55: H071 | B55: 71 | C55: 13 | D55: 8. Economia | E55: Infraestrutura | F55: Retomar investimentos em infraestrutura com programa de investimentos públicos | G55: Diretriz (sem meta) | H55: Em andamento | I55: Decreto 11.632/2023 instituiu o Novo PAC; execução em curso. | J55: Senado Federal - Legislação | K55: Oficial | L55: https://legis.senado.leg.br/norma/37473424 | M55: 11/08/2023 | N55: 26/10/2026
A56: H079 | B56: 79 | C56: 15 | D56: 8. Economia | E56: Estatais | F56: Oposição à privatização dos Correios | G56: Diretriz (sem meta) | H56: Em andamento | I56: Governo declarou oposição à privatização; não localizei ato de privatização no mandato. | J56: Poder360 (notícia) | K56: Imprensa | L56: https://www.poder360.com.br/brasil/e-preciso-dizer-nao-a-privatizacao-dos-correios-defende-lula/ | M56: s/d | N56: 26/10/2026
A57: H080 | B57: 80 | C57: 15 | D57: 8. Economia | E57: Bancos públicos | F57: Fortalecer BB, CEF, BNDES, BNB, BASA e Finep | G57: Diretriz (sem meta) | H57: Sem dados | I57: Ainda sem pesquisa de fonte; entra na próxima rodada. | N57: 26/10/2026
A58: H081 | B58: 81 | C58: 15 | D58: 8. Economia | E58: Ciência e tecnologia | F58: Recompor o sistema de fomento científico (FNDCT, CNPq, Capes) | G58: Diretriz (sem meta) | H58: Sem dados | I58: Ainda sem pesquisa de fonte; entra na próxima rodada. | N58: 26/10/2026
A59: H084 | B59: 84 | C59: 15 | D59: 8. Economia | E59: Economia criativa | F59: Estratégia econômica com economia criativa, transição digital e inteligência artificial | G59: Diretriz (sem meta) | H59: Sem dados | I59: Ainda sem pesquisa de fonte; entra na próxima rodada. | N59: 26/10/2026
A60: H085 | B60: 85 | C60: 15 | D60: 8. Economia | E60: Digital | F60: Transformação digital e internet de qualidade em todo o território | G60: Diretriz (sem meta) | H60: Sem dados | I60: Ainda sem pesquisa de fonte; entra na próxima rodada. | N60: 26/10/2026
A61: H087 | B61: 87 | C61: 16 | D61: 8. Economia | E61: Regiões | F61: Combater as desigualdades regionais | G61: Diretriz (sem meta) | H61: Sem dados | I61: Ainda sem pesquisa de fonte; entra na próxima rodada. | N61: 26/10/2026
A62: H088 | B62: 88 | C62: 16 | D62: 8. Economia | E62: Empreendedorismo | F62: Ambiente para empreendedores, cooperativismo e compras públicas para pequenos negócios | G62: Diretriz (sem meta) | H62: Sem dados | I62: Ainda sem pesquisa de fonte; entra na próxima rodada. | N62: 26/10/2026
A63: H089 | B63: 89 | C63: 16 | D63: 8. Economia | E63: Economia solidária | F63: Estimular economia solidária, economia criativa e empreendedorismo social | G63: Diretriz (sem meta) | H63: Sem dados | I63: Ainda sem pesquisa de fonte; entra na próxima rodada. | N63: 26/10/2026
A64: H015 | B64: 15 | C64: 4 | D64: 9. Segurança alimentar e agro | E64: Campo | F64: Reforma agrária e estímulo à economia solidária | G64: Diretriz (sem meta) | H64: Em andamento | I64: Governo informou 71 mil famílias assentadas em 2024; movimentos sociais contestam os números. | J64: IHU/Unisinos (reprodução de notícia) | K64: Imprensa | L64: https://ihu.unisinos.br/648437-governo-diz-ter-assentado-71-mil-familias-em-2024-mas-mst-contesta-dados | M64: 12/02/2025 | N64: 26/10/2026
A65: H018 | B65: 18 | C65: 5 | D65: 9. Segurança alimentar e agro | E65: Combate à fome | F65: Garantir ao menos três refeições de qualidade por dia a todos | G65: Meta numérica | H65: Em andamento | I65: Relatório da ONU (jul/2025) indicou a saída do Brasil do Mapa da Fome; a meta de três refeições para todos segue em curso. | J65: Jornal do Brasil (sobre relatório da ONU) | K65: Imprensa | L65: https://www.jb.com.br/brasil/direitos-humanos/2025/07/1056350-brasil-sai-do-mapa-da-fome-indica-relatorio-da-onu.html | M65: 28/07/2025 | N65: 26/10/2026
A66: H057 | B66: 57 | C66: 11 | D66: 9. Segurança alimentar e agro | E66: Abastecimento | F66: Política nacional de abastecimento, com estoques reguladores e apoio à agricultura familiar e orgânica | G66: Diretriz (sem meta) | H66: Sem dados | I66: Ainda sem pesquisa de fonte; entra na próxima rodada. | N66: 26/10/2026
A67: H065 | B67: 65 | C67: 12 | D67: 9. Segurança alimentar e agro | E67: Agricultura familiar | F67: Compras públicas e apoio à agricultura familiar para alimentos saudáveis | G67: Diretriz (sem meta) | H67: Em andamento | I67: Lei 14.660/2023 alterou o programa de alimentação escolar (prioridade a agricultoras na compra da agricultura familiar). | J67: Câmara dos Deputados - Legislação | K67: Oficial | L67: https://www2.camara.leg.br/legin/fed/lei/2023/lei-14660-23-agosto-2023-794585-norma-pl.html | M67: 23/08/2023 | N67: 26/10/2026
A68: H067 | B68: 67 | C68: 13 | D68: 9. Segurança alimentar e agro | E68: Pesquisa agrícola | F68: Fortalecer a Embrapa | G68: Diretriz (sem meta) | H68: Sem dados | I68: Ainda sem pesquisa de fonte; entra na próxima rodada. | N68: 26/10/2026
A69: H069 | B69: 69 | C69: 13 | D69: 9. Segurança alimentar e agro | E69: Agroindústria | F69: Agregar valor à produção agrícola e fortalecer a produção nacional de insumos e máquinas | G69: Diretriz (sem meta) | H69: Sem dados | I69: Ainda sem pesquisa de fonte; entra na próxima rodada. | N69: 26/10/2026
A70: H058 | B70: 58 | C70: 11 | D70: 10. Energia | E70: Combustíveis | F70: Nova política de preços dos combustíveis (abrasileirar o preço) | G70: Marco verificável | H70: Concluída | I70: Petrobras anunciou nova estratégia de preços e o fim da paridade de importação (PPI) em mai/2023. A decisão é da empresa. | J70: A Gazeta (coluna) | K70: Imprensa | L70: https://www.agazeta.com.br/dinheiro/lelio-monteiro/nova-estrategia-de-precos-de-combustiveis-da-petrobras-e-boa-ou-ruim-0523 | M70: 05/2023 | N70: 26/10/2026
A71: H075 | B71: 75 | C71: 14 | D71: 10. Energia | E71: Energia | F71: Garantir soberania e segurança energética, com fontes limpas e preços compatíveis | G71: Diretriz (sem meta) | H71: Sem dados | I71: Ainda sem pesquisa de fonte; entra na próxima rodada. | N71: 26/10/2026
A72: H077 | B72: 77 | C72: 14 | D72: 10. Energia | E72: Estatais | F72: Oposição à privatização da Petrobras e da PPSA | G72: Diretriz (sem meta) | H72: Em andamento | I72: Governo declarou em mai/2023 que não venderá a Petrobras; não localizei venda ou ato de privatização no mandato. | J72: O Povo (notícia) | K72: Imprensa | L72: https://www.opovo.com.br/noticias/economia/2023/05/11/lula-diz-que-nao-vai-vender-petrobras-e-correios-e-critica-privatizacao-da-eletrobras.html | M72: 11/05/2023 | N72: 26/10/2026
A73: H078 | B73: 78 | C73: 14 | D73: 10. Energia | E73: Estatais | F73: Oposição à privatização da Eletrobras e recuperação do seu papel | G73: Diretriz (sem meta) | H73: Não iniciada | I73: Empresa foi capitalizada em 2022, antes do mandato; localizei apenas críticas do presidente (mai/2023), sem ato de reversão. | J73: O Povo (notícia) | K73: Imprensa | L73: https://www.opovo.com.br/noticias/economia/2023/05/11/lula-diz-que-nao-vai-vender-petrobras-e-correios-e-critica-privatizacao-da-eletrobras.html | M73: 11/05/2023 | N73: 26/10/2026
A74: H078b | B74: 78b | C74: 15 | D74: 10. Energia | E74: Energia | F74: Dar continuidade ao Luz para Todos | G74: Diretriz (sem meta) | H74: Em andamento | I74: Decreto 11.628/2023 relançou o Programa Luz para Todos; execução em curso. | J74: Senado Federal - Legislação | K74: Oficial | L74: https://legis.senado.leg.br/norma/37456819 | M74: 04/08/2023 | N74: 26/10/2026
A75: H049 | B75: 49 | C75: 10 | D75: 11. Ambiente e clima | E75: Meio ambiente | F75: Combater o uso predatório dos recursos naturais e fortalecer o Sisnama e a Funai | G75: Diretriz (sem meta) | H75: Sem dados | I75: Ainda sem pesquisa de fonte; entra na próxima rodada. | N75: 26/10/2026
A76: H070 | B76: 70 | C76: 13 | D76: 11. Ambiente e clima | E76: Mineração | F76: Aperfeiçoar a regulação minerária e combater a mineração ilegal na Amazônia | G76: Diretriz (sem meta) | H76: Sem dados | I76: Ainda sem pesquisa de fonte; entra na próxima rodada. | N76: 26/10/2026
A77: H091 | B77: 91 | C77: 16 | D77: 11. Ambiente e clima | E77: Clima | F77: Cumprir e superar as metas de emissões do Acordo de Paris | G77: Meta numérica | H77: Em andamento | I77: Nova NDC entregue à ONU em nov/2024 (redução de 59% a 67% até 2035); o cumprimento será aferido até 2035. | J77: Agência Gov (EBC) | K77: Agência pública | L77: https://agenciagov.ebc.com.br/noticias/202411/brasil-entrega-a-onu-nova-ndc-alinhada-ao-acordo-de-paris | M77: 11/2024 | N77: 26/10/2026
A78: H094 | B78: 94 | C78: 17 | D78: 11. Ambiente e clima | E78: Amazônia | F78: Combate ao desmatamento ilegal e desmatamento líquido zero | G78: Meta numérica | H78: Em andamento | I78: Desmatamento na Amazônia caiu cerca de 11% no PRODES 2025, segundo reportagem sobre dados do INPE; meta de desmatamento líquido zero não atingida. | J78: Forbes Brasil (sobre dados do INPE) | K78: Imprensa | L78: https://forbes.com.br/forbes-esg/2025/10/amazonia-tem-queda-de-11-no-desmatamento-e-terceira-menor-area-destruida-em-um-ano/ | M78: 10/2025 | N78: 26/10/2026
A79: H095 | B79: 95 | C79: 17 | D79: 11. Ambiente e clima | E79: Biodiversidade | F79: Conservar os biomas, a zona econômica exclusiva e a Amazônia Azul | G79: Diretriz (sem meta) | H79: Sem dados | I79: Ainda sem pesquisa de fonte; entra na próxima rodada. | N79: 26/10/2026
A80: H096 | B80: 96 | C80: 17 | D80: 11. Ambiente e clima | E80: Biodiversidade | F80: Destravar o potencial da economia da biodiversidade | G80: Diretriz (sem meta) | H80: Sem dados | I80: Ainda sem pesquisa de fonte; entra na próxima rodada. | N80: 26/10/2026
A81: H013 | B81: 13 | C81: 4 | D81: 12. Trabalho e previdência | E81: Trabalho | F81: Nova legislação trabalhista com proteção a autônomos e plataformas e revogação de marcos da reforma de 2017 | G81: Diretriz (sem meta) | H81: Sem dados | I81: Pesquisado nesta rodada sem fonte consolidada. Verificar PLP 12/2024 (motoristas de aplicativo) e a Lei 13.467/2017. | N81: 26/10/2026
A82: H014 | B82: 14 | C82: 4 | D82: 12. Trabalho e previdência | E82: Sindicatos | F82: Incentivar a reestruturação sindical, a negociação coletiva e o direito de greve | G82: Diretriz (sem meta) | H82: Sem dados | I82: Ainda sem pesquisa de fonte; entra na próxima rodada. | N82: 26/10/2026
A83: H016 | B83: 16 | C83: 4 | D83: 12. Trabalho e previdência | E83: Salário mínimo | F83: Retomar a política de valorização do salário mínimo | G83: Marco verificável | H83: Concluída | I83: Lei 14.663/2023 fixou a nova regra de reajuste. | J83: Senado Federal - Legislação | K83: Oficial | L83: https://legis.senado.leg.br/norma/37536044/publicacao/37540745 | M83: 28/08/2023 | N83: 26/10/2026
A84: H017 | B84: 17 | C84: 4 | D84: 12. Trabalho e previdência | E84: Previdência | F84: Reconstruir a seguridade e a previdência social | G84: Diretriz (sem meta) | H84: Sem dados | I84: Pesquisado nesta rodada sem fonte consolidada. | N84: 26/10/2026
A85: H064 | B85: 64 | C85: 12 | D85: 13. Soberania e política externa | E85: Comércio exterior | F85: Ampliar acordos comerciais relevantes | G85: Diretriz (sem meta) | H85: Em andamento | I85: Acordo Mercosul-União Europeia promulgado pelo Congresso em 17/03/2026. | J85: Agência Senado | K85: Oficial | L85: https://www12.senado.leg.br/noticias/materias/2026/03/17/congresso-promulga-acordo-mercosul-uniao-europeia | M85: 17/03/2026 | N85: 26/10/2026
A86: H100 | B86: 100 | C86: 17 | D86: 13. Soberania e política externa | E86: Política externa | F86: Recuperar a política externa ativa e altiva e a cooperação Sul-Sul | G86: Diretriz (sem meta) | H86: Sem dados | I86: Ainda sem pesquisa de fonte; entra na próxima rodada. | N86: 26/10/2026
A87: H101 | B87: 101 | C87: 18 | D87: 13. Soberania e política externa | E87: Integração regional | F87: Fortalecer Mercosul, Unasul, Celac e Brics | G87: Diretriz (sem meta) | H87: Sem dados | I87: Ainda sem pesquisa de fonte; entra na próxima rodada. | N87: 26/10/2026
A88: H102 | B88: 102 | C88: 18 | D88: 13. Soberania e política externa | E88: Brasileiros no exterior | F88: Retomar e ampliar políticas para brasileiros no exterior | G88: Diretriz (sem meta) | H88: Sem dados | I88: Ainda sem pesquisa de fonte; entra na próxima rodada. | N88: 26/10/2026
A89: H103 | B89: 103 | C89: 18 | D89: 13. Soberania e política externa | E89: Defesa | F89: Políticas de defesa e inteligência, com Forças Armadas dentro da Constituição | G89: Diretriz (sem meta) | H89: Sem dados | I89: Ainda sem pesquisa de fonte; entra na próxima rodada. | N89: 26/10/2026

Sheet Gastos
A1: ID da proposta | B1: Projeto / ação | C1: Valor empenhado (R$) | D1: Valor pago (R$) | E1: Data de referência | F1: Portal / fonte | G1: Link oficial da fonte | H1: Registrado por | I1: Observações | J1: Eixo (automático) | K1: Situação (automática)
J2: =IF(A2="","",IFERROR(INDEX(Propostas!$B:$B,MATCH(A2,Propostas!$A:$A,0)),IFERROR(INDEX('Lula 2022 (2023-2026)'!$D:$D,MATCH(A2,'Lula 2022 (2023-2026)'!$A:$A,0)),"ID inexistente"))) | K2: =IF(A2="","",IF(AND(ISNA(MATCH(A2,Propostas!$A:$A,0)),ISNA(MATCH(A2,'Lula 2022 (2023-2026)'!$A:$A,0))),"ID inexistente",IF(OR(F2="",NOT(ISNUMBER(E2))),"Sem fonte ou data",IF(NOT(AND(LEFT(G2,8)="https://",OR(ISNUMBER(SEARCH(".gov.br",G2)),ISNUMBER(SEARCH(".leg.br",G2)),ISNUMBER(SEARCH(".jus.br",G2)),ISNUMBER(SEARCH(".mp.br",G2))))),"Sem link oficial",IF(OR(NOT(ISNUMBER(C2)),NOT(ISNUMBER(D2)),D2<0,D2>C2),"Valor inválido","Verificável")))))
J3: =IF(A3="","",IFERROR(INDEX(Propostas!$B:$B,MATCH(A3,Propostas!$A:$A,0)),IFERROR(INDEX('Lula 2022 (2023-2026)'!$D:$D,MATCH(A3,'Lula 2022 (2023-2026)'!$A:$A,0)),"ID inexistente"))) | K3: =IF(A3="","",IF(AND(ISNA(MATCH(A3,Propostas!$A:$A,0)),ISNA(MATCH(A3,'Lula 2022 (2023-2026)'!$A:$A,0))),"ID inexistente",IF(OR(F3="",NOT(ISNUMBER(E3))),"Sem fonte ou data",IF(NOT(AND(LEFT(G3,8)="https://",OR(ISNUMBER(SEARCH(".gov.br",G3)),ISNUMBER(SEARCH(".leg.br",G3)),ISNUMBER(SEARCH(".jus.br",G3)),ISNUMBER(SEARCH(".mp.br",G3))))),"Sem link oficial",IF(OR(NOT(ISNUMBER(C3)),NOT(ISNUMBER(D3)),D3<0,D3>C3),"Valor inválido","Verificável")))))
J4: =IF(A4="","",IFERROR(INDEX(Propostas!$B:$B,MATCH(A4,Propostas!$A:$A,0)),IFERROR(INDEX('Lula 2022 (2023-2026)'!$D:$D,MATCH(A4,'Lula 2022 (2023-2026)'!$A:$A,0)),"ID inexistente"))) | K4: =IF(A4="","",IF(AND(ISNA(MATCH(A4,Propostas!$A:$A,0)),ISNA(MATCH(A4,'Lula 2022 (2023-2026)'!$A:$A,0))),"ID inexistente",IF(OR(F4="",NOT(ISNUMBER(E4))),"Sem fonte ou data",IF(NOT(AND(LEFT(G4,8)="https://",OR(ISNUMBER(SEARCH(".gov.br",G4)),ISNUMBER(SEARCH(".leg.br",G4)),ISNUMBER(SEARCH(".jus.br",G4)),ISNUMBER(SEARCH(".mp.br",G4))))),"Sem link oficial",IF(OR(NOT(ISNUMBER(C4)),NOT(ISNUMBER(D4)),D4<0,D4>C4),"Valor inválido","Verificável")))))
J5: =IF(A5="","",IFERROR(INDEX(Propostas!$B:$B,MATCH(A5,Propostas!$A:$A,0)),IFERROR(INDEX('Lula 2022 (2023-2026)'!$D:$D,MATCH(A5,'Lula 2022 (2023-2026)'!$A:$A,0)),"ID inexistente"))) | K5: =IF(A5="","",IF(AND(ISNA(MATCH(A5,Propostas!$A:$A,0)),ISNA(MATCH(A5,'Lula 2022 (2023-2026)'!$A:$A,0))),"ID inexistente",IF(OR(F5="",NOT(ISNUMBER(E5))),"Sem fonte ou data",IF(NOT(AND(LEFT(G5,8)="https://",OR(ISNUMBER(SEARCH(".gov.br",G5)),ISNUMBER(SEARCH(".leg.br",G5)),ISNUMBER(SEARCH(".jus.br",G5)),ISNUMBER(SEARCH(".mp.br",G5))))),"Sem link oficial",IF(OR(NOT(ISNUMBER(C5)),NOT(ISNUMBER(D5)),D5<0,D5>C5),"Valor inválido","Verificável")))))
J6: =IF(A6="","",IFERROR(INDEX(Propostas!$B:$B,MATCH(A6,Propostas!$A:$A,0)),IFERROR(INDEX('Lula 2022 (2023-2026)'!$D:$D,MATCH(A6,'Lula 2022 (2023-2026)'!$A:$A,0)),"ID inexistente"))) | K6: =IF(A6="","",IF(AND(ISNA(MATCH(A6,Propostas!$A:$A,0)),ISNA(MATCH(A6,'Lula 2022 (2023-2026)'!$A:$A,0))),"ID inexistente",IF(OR(F6="",NOT(ISNUMBER(E6))),"Sem fonte ou data",IF(NOT(AND(LEFT(G6,8)="https://",OR(ISNUMBER(SEARCH(".gov.br",G6)),ISNUMBER(SEARCH(".leg.br",G6)),ISNUMBER(SEARCH(".jus.br",G6)),ISNUMBER(SEARCH(".mp.br",G6))))),"Sem link oficial",IF(OR(NOT(ISNUMBER(C6)),NOT(ISNUMBER(D6)),D6<0,D6>C6),"Valor inválido","Verificável")))))
J7: =IF(A7="","",IFERROR(INDEX(Propostas!$B:$B,MATCH(A7,Propostas!$A:$A,0)),IFERROR(INDEX('Lula 2022 (2023-2026)'!$D:$D,MATCH(A7,'Lula 2022 (2023-2026)'!$A:$A,0)),"ID inexistente"))) | K7: =IF(A7="","",IF(AND(ISNA(MATCH(A7,Propostas!$A:$A,0)),ISNA(MATCH(A7,'Lula 2022 (2023-2026)'!$A:$A,0))),"ID inexistente",IF(OR(F7="",NOT(ISNUMBER(E7))),"Sem fonte ou data",IF(NOT(AND(LEFT(G7,8)="https://",OR(ISNUMBER(SEARCH(".gov.br",G7)),ISNUMBER(SEARCH(".leg.br",G7)),ISNUMBER(SEARCH(".jus.br",G7)),ISNUMBER(SEARCH(".mp.br",G7))))),"Sem link oficial",IF(OR(NOT(ISNUMBER(C7)),NOT(ISNUMBER(D7)),D7<0,D7>C7),"Valor inválido","Verificável")))))
J8: =IF(A8="","",IFERROR(INDEX(Propostas!$B:$B,MATCH(A8,Propostas!$A:$A,0)),IFERROR(INDEX('Lula 2022 (2023-2026)'!$D:$D,MATCH(A8,'Lula 2022 (2023-2026)'!$A:$A,0)),"ID inexistente"))) | K8: =IF(A8="","",IF(AND(ISNA(MATCH(A8,Propostas!$A:$A,0)),ISNA(MATCH(A8,'Lula 2022 (2023-2026)'!$A:$A,0))),"ID inexistente",IF(OR(F8="",NOT(ISNUMBER(E8))),"Sem fonte ou data",IF(NOT(AND(LEFT(G8,8)="https://",OR(ISNUMBER(SEARCH(".gov.br",G8)),ISNUMBER(SEARCH(".leg.br",G8)),ISNUMBER(SEARCH(".jus.br",G8)),ISNUMBER(SEARCH(".mp.br",G8))))),"Sem link oficial",IF(OR(NOT(ISNUMBER(C8)),NOT(ISNUMBER(D8)),D8<0,D8>C8),"Valor inválido","Verificável")))))
J9: =IF(A9="","",IFERROR(INDEX(Propostas!$B:$B,MATCH(A9,Propostas!$A:$A,0)),IFERROR(INDEX('Lula 2022 (2023-2026)'!$D:$D,MATCH(A9,'Lula 2022 (2023-2026)'!$A:$A,0)),"ID inexistente"))) | K9: =IF(A9="","",IF(AND(ISNA(MATCH(A9,Propostas!$A:$A,0)),ISNA(MATCH(A9,'Lula 2022 (2023-2026)'!$A:$A,0))),"ID inexistente",IF(OR(F9="",NOT(ISNUMBER(E9))),"Sem fonte ou data",IF(NOT(AND(LEFT(G9,8)="https://",OR(ISNUMBER(SEARCH(".gov.br",G9)),ISNUMBER(SEARCH(".leg.br",G9)),ISNUMBER(SEARCH(".jus.br",G9)),ISNUMBER(SEARCH(".mp.br",G9))))),"Sem link oficial",IF(OR(NOT(ISNUMBER(C9)),NOT(ISNUMBER(D9)),D9<0,D9>C9),"Valor inválido","Verificável")))))
J10: =IF(A10="","",IFERROR(INDEX(Propostas!$B:$B,MATCH(A10,Propostas!$A:$A,0)),IFERROR(INDEX('Lula 2022 (2023-2026)'!$D:$D,MATCH(A10,'Lula 2022 (2023-2026)'!$A:$A,0)),"ID inexistente"))) | K10: =IF(A10="","",IF(AND(ISNA(MATCH(A10,Propostas!$A:$A,0)),ISNA(MATCH(A10,'Lula 2022 (2023-2026)'!$A:$A,0))),"ID inexistente",IF(OR(F10="",NOT(ISNUMBER(E10))),"Sem fonte ou data",IF(NOT(AND(LEFT(G10,8)="https://",OR(ISNUMBER(SEARCH(".gov.br",G10)),ISNUMBER(SEARCH(".leg.br",G10)),ISNUMBER(SEARCH(".jus.br",G10)),ISNUMBER(SEARCH(".mp.br",G10))))),"Sem link oficial",IF(OR(NOT(ISNUMBER(C10)),NOT(ISNUMBER(D10)),D10<0,D10>C10),"Valor inválido","Verificável")))))
J11: =IF(A11="","",IFERROR(INDEX(Propostas!$B:$B,MATCH(A11,Propostas!$A:$A,0)),IFERROR(INDEX('Lula 2022 (2023-2026)'!$D:$D,MATCH(A11,'Lula 2022 (2023-2026)'!$A:$A,0)),"ID inexistente"))) | K11: =IF(A11="","",IF(AND(ISNA(MATCH(A11,Propostas!$A:$A,0)),ISNA(MATCH(A11,'Lula 2022 (2023-2026)'!$A:$A,0))),"ID inexistente",IF(OR(F11="",NOT(ISNUMBER(E11))),"Sem fonte ou data",IF(NOT(AND(LEFT(G11,8)="https://",OR(ISNUMBER(SEARCH(".gov.br",G11)),ISNUMBER(SEARCH(".leg.br",G11)),ISNUMBER(SEARCH(".jus.br",G11)),ISNUMBER(SEARCH(".mp.br",G11))))),"Sem link oficial",IF(OR(NOT(ISNUMBER(C11)),NOT(ISNUMBER(D11)),D11<0,D11>C11),"Valor inválido","Verificável")))))
J12: =IF(A12="","",IFERROR(INDEX(Propostas!$B:$B,MATCH(A12,Propostas!$A:$A,0)),IFERROR(INDEX('Lula 2022 (2023-2026)'!$D:$D,MATCH(A12,'Lula 2022 (2023-2026)'!$A:$A,0)),"ID inexistente"))) | K12: =IF(A12="","",IF(AND(ISNA(MATCH(A12,Propostas!$A:$A,0)),ISNA(MATCH(A12,'Lula 2022 (2023-2026)'!$A:$A,0))),"ID inexistente",IF(OR(F12="",NOT(ISNUMBER(E12))),"Sem fonte ou data",IF(NOT(AND(LEFT(G12,8)="https://",OR(ISNUMBER(SEARCH(".gov.br",G12)),ISNUMBER(SEARCH(".leg.br",G12)),ISNUMBER(SEARCH(".jus.br",G12)),ISNUMBER(SEARCH(".mp.br",G12))))),"Sem link oficial",IF(OR(NOT(ISNUMBER(C12)),NOT(ISNUMBER(D12)),D12<0,D12>C12),"Valor inválido","Verificável")))))
J13: =IF(A13="","",IFERROR(INDEX(Propostas!$B:$B,MATCH(A13,Propostas!$A:$A,0)),IFERROR(INDEX('Lula 2022 (2023-2026)'!$D:$D,MATCH(A13,'Lula 2022 (2023-2026)'!$A:$A,0)),"ID inexistente"))) | K13: =IF(A13="","",IF(AND(ISNA(MATCH(A13,Propostas!$A:$A,0)),ISNA(MATCH(A13,'Lula 2022 (2023-2026)'!$A:$A,0))),"ID inexistente",IF(OR(F13="",NOT(ISNUMBER(E13))),"Sem fonte ou data",IF(NOT(AND(LEFT(G13,8)="https://",OR(ISNUMBER(SEARCH(".gov.br",G13)),ISNUMBER(SEARCH(".leg.br",G13)),ISNUMBER(SEARCH(".jus.br",G13)),ISNUMBER(SEARCH(".mp.br",G13))))),"Sem link oficial",IF(OR(NOT(ISNUMBER(C13)),NOT(ISNUMBER(D13)),D13<0,D13>C13),"Valor inválido","Verificável")))))
... J301: =IF(A301="","",IFERROR(INDEX(Propostas!$B:$B,MATCH(A301,Propostas!$A:$A,0)),IFERROR(INDEX('Lula 2022 (2023-2026)'!$D:$D,MATCH(A301,'Lula 2022 (2023-2026)'!$A:$A,0)),"ID inexistente"))) | K301: =IF(A301="","",IF(AND(ISNA(MATCH(A301,Propostas!$A:$A,0)),ISNA(MATCH(A301,'Lula 2022 (2023-2026)'!$A:$A,0))),"ID inexistente",IF(OR(F301="",NOT(ISNUMBER(E301))),"Sem fonte ou data",IF(NOT(AND(LEFT(G301,8)="https://",OR(ISNUMBER(SEARCH(".gov.br",G301)),ISNUMBER(SEARCH(".leg.br",G301)),ISNUMBER(SEARCH(".jus.br",G301)),ISNUMBER(SEARCH(".mp.br",G301))))),"Sem link oficial",IF(OR(NOT(ISNUMBER(C301)),NOT(ISNUMBER(D301)),D301<0,D301>C301),"Valor inválido","Verificável")))))

Sheet Resumo
A1: Medidor do Programa de Governo: resumo
A2: Todos os números abaixo são fórmulas e se atualizam sozinhos quando a aba Propostas é editada.
A4: Avanço médio geral | B4: =IFERROR(AVERAGE(Propostas!$K$2:$K$500),0) -> 0
A5: Propostas concluídas (%) | B5: =IFERROR(COUNTIF(Propostas!$J$2:$J$500,"Concluída")/COUNTA(Propostas!$A$2:$A$500),0) -> 0
A7: Eixo | B7: Total | C7: Não iniciada | D7: Em andamento | E7: Concluída | F7: Sem dados | G7: % concluídas | H7: Avanço médio
A8: 1. Democracia e Estado | B8: =COUNTIF(Propostas!$B$2:$B$500,$A8) -> 18 | C8: =COUNTIFS(Propostas!$B$2:$B$500,$A8,Propostas!$J$2:$J$500,"Não iniciada") -> 18 | D8: =COUNTIFS(Propostas!$B$2:$B$500,$A8,Propostas!$J$2:$J$500,"Em andamento") -> 0 | E8: =COUNTIFS(Propostas!$B$2:$B$500,$A8,Propostas!$J$2:$J$500,"Concluída") -> 0 | F8: =COUNTIFS(Propostas!$B$2:$B$500,$A8,Propostas!$J$2:$J$500,"Sem dados") -> 0 | G8: =IFERROR(E8/B8,0) -> 0 | H8: =IFERROR(AVERAGEIFS(Propostas!$K$2:$K$500,Propostas!$B$2:$B$500,$A8),0) -> 0
A9: 2. Desigualdades | B9: =COUNTIF(Propostas!$B$2:$B$500,$A9) -> 39 | C9: =COUNTIFS(Propostas!$B$2:$B$500,$A9,Propostas!$J$2:$J$500,"Não iniciada") -> 39 | D9: =COUNTIFS(Propostas!$B$2:$B$500,$A9,Propostas!$J$2:$J$500,"Em andamento") -> 0 | E9: =COUNTIFS(Propostas!$B$2:$B$500,$A9,Propostas!$J$2:$J$500,"Concluída") -> 0 | F9: =COUNTIFS(Propostas!$B$2:$B$500,$A9,Propostas!$J$2:$J$500,"Sem dados") -> 0 | G9: =IFERROR(E9/B9,0) -> 0 | H9: =IFERROR(AVERAGEIFS(Propostas!$K$2:$K$500,Propostas!$B$2:$B$500,$A9),0) -> 0
A10: 3. Segurança pública | B10: =COUNTIF(Propostas!$B$2:$B$500,$A10) -> 17 | C10: =COUNTIFS(Propostas!$B$2:$B$500,$A10,Propostas!$J$2:$J$500,"Não iniciada") -> 17 | D10: =COUNTIFS(Propostas!$B$2:$B$500,$A10,Propostas!$J$2:$J$500,"Em andamento") -> 0 | E10: =COUNTIFS(Propostas!$B$2:$B$500,$A10,Propostas!$J$2:$J$500,"Concluída") -> 0 | F10: =COUNTIFS(Propostas!$B$2:$B$500,$A10,Propostas!$J$2:$J$500,"Sem dados") -> 0 | G10: =IFERROR(E10/B10,0) -> 0 | H10: =IFERROR(AVERAGEIFS(Propostas!$K$2:$K$500,Propostas!$B$2:$B$500,$A10),0) -> 0
A11: 4. Educação | B11: =COUNTIF(Propostas!$B$2:$B$500,$A11) -> 21 | C11: =COUNTIFS(Propostas!$B$2:$B$500,$A11,Propostas!$J$2:$J$500,"Não iniciada") -> 21 | D11: =COUNTIFS(Propostas!$B$2:$B$500,$A11,Propostas!$J$2:$J$500,"Em andamento") -> 0 | E11: =COUNTIFS(Propostas!$B$2:$B$500,$A11,Propostas!$J$2:$J$500,"Concluída") -> 0 | F11: =COUNTIFS(Propostas!$B$2:$B$500,$A11,Propostas!$J$2:$J$500,"Sem dados") -> 0 | G11: =IFERROR(E11/B11,0) -> 0 | H11: =IFERROR(AVERAGEIFS(Propostas!$K$2:$K$500,Propostas!$B$2:$B$500,$A11),0) -> 0
A12: 5. Saúde | B12: =COUNTIF(Propostas!$B$2:$B$500,$A12) -> 27 | C12: =COUNTIFS(Propostas!$B$2:$B$500,$A12,Propostas!$J$2:$J$500,"Não iniciada") -> 27 | D12: =COUNTIFS(Propostas!$B$2:$B$500,$A12,Propostas!$J$2:$J$500,"Em andamento") -> 0 | E12: =COUNTIFS(Propostas!$B$2:$B$500,$A12,Propostas!$J$2:$J$500,"Concluída") -> 0 | F12: =COUNTIFS(Propostas!$B$2:$B$500,$A12,Propostas!$J$2:$J$500,"Sem dados") -> 0 | G12: =IFERROR(E12/B12,0) -> 0 | H12: =IFERROR(AVERAGEIFS(Propostas!$K$2:$K$500,Propostas!$B$2:$B$500,$A12),0) -> 0
A13: 6. Cultura e esporte | B13: =COUNTIF(Propostas!$B$2:$B$500,$A13) -> 19 | C13: =COUNTIFS(Propostas!$B$2:$B$500,$A13,Propostas!$J$2:$J$500,"Não iniciada") -> 19 | D13: =COUNTIFS(Propostas!$B$2:$B$500,$A13,Propostas!$J$2:$J$500,"Em andamento") -> 0 | E13: =COUNTIFS(Propostas!$B$2:$B$500,$A13,Propostas!$J$2:$J$500,"Concluída") -> 0 | F13: =COUNTIFS(Propostas!$B$2:$B$500,$A13,Propostas!$J$2:$J$500,"Sem dados") -> 0 | G13: =IFERROR(E13/B13,0) -> 0 | H13: =IFERROR(AVERAGEIFS(Propostas!$K$2:$K$500,Propostas!$B$2:$B$500,$A13),0) -> 0
A14: 7. Direito à cidade | B14: =COUNTIF(Propostas!$B$2:$B$500,$A14) -> 14 | C14: =COUNTIFS(Propostas!$B$2:$B$500,$A14,Propostas!$J$2:$J$500,"Não iniciada") -> 14 | D14: =COUNTIFS(Propostas!$B$2:$B$500,$A14,Propostas!$J$2:$J$500,"Em andamento") -> 0 | E14: =COUNTIFS(Propostas!$B$2:$B$500,$A14,Propostas!$J$2:$J$500,"Concluída") -> 0 | F14: =COUNTIFS(Propostas!$B$2:$B$500,$A14,Propostas!$J$2:$J$500,"Sem dados") -> 0 | G14: =IFERROR(E14/B14,0) -> 0 | H14: =IFERROR(AVERAGEIFS(Propostas!$K$2:$K$500,Propostas!$B$2:$B$500,$A14),0) -> 0
A15: 8. Economia | B15: =COUNTIF(Propostas!$B$2:$B$500,$A15) -> 36 | C15: =COUNTIFS(Propostas!$B$2:$B$500,$A15,Propostas!$J$2:$J$500,"Não iniciada") -> 36 | D15: =COUNTIFS(Propostas!$B$2:$B$500,$A15,Propostas!$J$2:$J$500,"Em andamento") -> 0 | E15: =COUNTIFS(Propostas!$B$2:$B$500,$A15,Propostas!$J$2:$J$500,"Concluída") -> 0 | F15: =COUNTIFS(Propostas!$B$2:$B$500,$A15,Propostas!$J$2:$J$500,"Sem dados") -> 0 | G15: =IFERROR(E15/B15,0) -> 0 | H15: =IFERROR(AVERAGEIFS(Propostas!$K$2:$K$500,Propostas!$B$2:$B$500,$A15),0) -> 0
A16: 9. Segurança alimentar e agro | B16: =COUNTIF(Propostas!$B$2:$B$500,$A16) -> 27 | C16: =COUNTIFS(Propostas!$B$2:$B$500,$A16,Propostas!$J$2:$J$500,"Não iniciada") -> 27 | D16: =COUNTIFS(Propostas!$B$2:$B$500,$A16,Propostas!$J$2:$J$500,"Em andamento") -> 0 | E16: =COUNTIFS(Propostas!$B$2:$B$500,$A16,Propostas!$J$2:$J$500,"Concluída") -> 0 | F16: =COUNTIFS(Propostas!$B$2:$B$500,$A16,Propostas!$J$2:$J$500,"Sem dados") -> 0 | G16: =IFERROR(E16/B16,0) -> 0 | H16: =IFERROR(AVERAGEIFS(Propostas!$K$2:$K$500,Propostas!$B$2:$B$500,$A16),0) -> 0
A17: 10. Energia | B17: =COUNTIF(Propostas!$B$2:$B$500,$A17) -> 16 | C17: =COUNTIFS(Propostas!$B$2:$B$500,$A17,Propostas!$J$2:$J$500,"Não iniciada") -> 16 | D17: =COUNTIFS(Propostas!$B$2:$B$500,$A17,Propostas!$J$2:$J$500,"Em andamento") -> 0 | E17: =COUNTIFS(Propostas!$B$2:$B$500,$A17,Propostas!$J$2:$J$500,"Concluída") -> 0 | F17: =COUNTIFS(Propostas!$B$2:$B$500,$A17,Propostas!$J$2:$J$500,"Sem dados") -> 0 | G17: =IFERROR(E17/B17,0) -> 0 | H17: =IFERROR(AVERAGEIFS(Propostas!$K$2:$K$500,Propostas!$B$2:$B$500,$A17),0) -> 0
A18: 11. Ambiente e clima | B18: =COUNTIF(Propostas!$B$2:$B$500,$A18) -> 18 | C18: =COUNTIFS(Propostas!$B$2:$B$500,$A18,Propostas!$J$2:$J$500,"Não iniciada") -> 18 | D18: =COUNTIFS(Propostas!$B$2:$B$500,$A18,Propostas!$J$2:$J$500,"Em andamento") -> 0 | E18: =COUNTIFS(Propostas!$B$2:$B$500,$A18,Propostas!$J$2:$J$500,"Concluída") -> 0 | F18: =COUNTIFS(Propostas!$B$2:$B$500,$A18,Propostas!$J$2:$J$500,"Sem dados") -> 0 | G18: =IFERROR(E18/B18,0) -> 0 | H18: =IFERROR(AVERAGEIFS(Propostas!$K$2:$K$500,Propostas!$B$2:$B$500,$A18),0) -> 0
A19: 12. Trabalho e previdência | B19: =COUNTIF(Propostas!$B$2:$B$500,$A19) -> 20 | C19: =COUNTIFS(Propostas!$B$2:$B$500,$A19,Propostas!$J$2:$J$500,"Não iniciada") -> 20 | D19: =COUNTIFS(Propostas!$B$2:$B$500,$A19,Propostas!$J$2:$J$500,"Em andamento") -> 0 | E19: =COUNTIFS(Propostas!$B$2:$B$500,$A19,Propostas!$J$2:$J$500,"Concluída") -> 0 | F19: =COUNTIFS(Propostas!$B$2:$B$500,$A19,Propostas!$J$2:$J$500,"Sem dados") -> 0 | G19: =IFERROR(E19/B19,0) -> 0 | H19: =IFERROR(AVERAGEIFS(Propostas!$K$2:$K$500,Propostas!$B$2:$B$500,$A19),0) -> 0
A20: 13. Soberania e política externa | B20: =COUNTIF(Propostas!$B$2:$B$500,$A20) -> 17 | C20: =COUNTIFS(Propostas!$B$2:$B$500,$A20,Propostas!$J$2:$J$500,"Não iniciada") -> 17 | D20: =COUNTIFS(Propostas!$B$2:$B$500,$A20,Propostas!$J$2:$J$500,"Em andamento") -> 0 | E20: =COUNTIFS(Propostas!$B$2:$B$500,$A20,Propostas!$J$2:$J$500,"Concluída") -> 0 | F20: =COUNTIFS(Propostas!$B$2:$B$500,$A20,Propostas!$J$2:$J$500,"Sem dados") -> 0 | G20: =IFERROR(E20/B20,0) -> 0 | H20: =IFERROR(AVERAGEIFS(Propostas!$K$2:$K$500,Propostas!$B$2:$B$500,$A20),0) -> 0
A21: Total | B21: =SUM(B8:B20) -> 289 | C21: =SUM(C8:C20) -> 289 | D21: =SUM(D8:D20) -> 0 | E21: =SUM(E8:E20) -> 0 | F21: =SUM(F8:F20) -> 0 | G21: =IFERROR(E21/B21,0) -> 0 | H21: =IFERROR(AVERAGE(Propostas!$K$2:$K$500),0) -> 0
A24: Tipo de proposta | B24: Total | C24: Não iniciada | D24: Em andamento | E24: Concluída | F24: Sem dados | G24: % concluídas | H24: Avanço médio
A25: Meta numérica | B25: =COUNTIF(Propostas!$F$2:$F$500,$A25) -> 18 | C25: =COUNTIFS(Propostas!$F$2:$F$500,$A25,Propostas!$J$2:$J$500,"Não iniciada") -> 18 | D25: =COUNTIFS(Propostas!$F$2:$F$500,$A25,Propostas!$J$2:$J$500,"Em andamento") -> 0 | E25: =COUNTIFS(Propostas!$F$2:$F$500,$A25,Propostas!$J$2:$J$500,"Concluída") -> 0 | F25: =COUNTIFS(Propostas!$F$2:$F$500,$A25,Propostas!$J$2:$J$500,"Sem dados") -> 0 | G25: =IFERROR(E25/B25,0) -> 0 | H25: =IFERROR(AVERAGEIFS(Propostas!$K$2:$K$500,Propostas!$F$2:$F$500,$A25),0) -> 0
A26: Marco verificável | B26: =COUNTIF(Propostas!$F$2:$F$500,$A26) -> 57 | C26: =COUNTIFS(Propostas!$F$2:$F$500,$A26,Propostas!$J$2:$J$500,"Não iniciada") -> 57 | D26: =COUNTIFS(Propostas!$F$2:$F$500,$A26,Propostas!$J$2:$J$500,"Em andamento") -> 0 | E26: =COUNTIFS(Propostas!$F$2:$F$500,$A26,Propostas!$J$2:$J$500,"Concluída") -> 0 | F26: =COUNTIFS(Propostas!$F$2:$F$500,$A26,Propostas!$J$2:$J$500,"Sem dados") -> 0 | G26: =IFERROR(E26/B26,0) -> 0 | H26: =IFERROR(AVERAGEIFS(Propostas!$K$2:$K$500,Propostas!$F$2:$F$500,$A26),0) -> 0
A27: Diretriz (sem meta) | B27: =COUNTIF(Propostas!$F$2:$F$500,$A27) -> 214 | C27: =COUNTIFS(Propostas!$F$2:$F$500,$A27,Propostas!$J$2:$J$500,"Não iniciada") -> 214 | D27: =COUNTIFS(Propostas!$F$2:$F$500,$A27,Propostas!$J$2:$J$500,"Em andamento") -> 0 | E27: =COUNTIFS(Propostas!$F$2:$F$500,$A27,Propostas!$J$2:$J$500,"Concluída") -> 0 | F27: =COUNTIFS(Propostas!$F$2:$F$500,$A27,Propostas!$J$2:$J$500,"Sem dados") -> 0 | G27: =IFERROR(E27/B27,0) -> 0 | H27: =IFERROR(AVERAGEIFS(Propostas!$K$2:$K$500,Propostas!$F$2:$F$500,$A27),0) -> 0
A28: Total | B28: =SUM(B25:B27) -> 289 | C28: =SUM(C25:C27) -> 289 | D28: =SUM(D25:D27) -> 0 | E28: =SUM(E25:E27) -> 0 | F28: =SUM(F25:F27) -> 0 | G28: =IFERROR(E28/B28,0) -> 0 | H28: =IFERROR(AVERAGE(Propostas!$K$2:$K$500),0) -> 0
A30: Conferência: o total por eixo deve ser igual ao total por tipo.
A31: Confere? | B31: =IF(B21=B28,"OK","DIVERGE") -> OK
A35: Gastos verificáveis (aba Gastos)
A36: Total pago (R$) | B36: =SUMIFS(Gastos!$D$2:$D$301,Gastos!$K$2:$K$301,"Verificável") -> 0
A37: Total empenhado (R$) | B37: =SUMIFS(Gastos!$C$2:$C$301,Gastos!$K$2:$K$301,"Verificável") -> 0
A38: Registros verificáveis | B38: =COUNTIF(Gastos!$K$2:$K$301,"Verificável") -> 0
A39: Registros não contabilizados | B39: =COUNTA(Gastos!$A$2:$A$301)-B38 -> 0
A42: Lula 2022 (mandato 2023-2026): balanço
A43: Itens no balanço | B43: =COUNTA('Lula 2022 (2023-2026)'!$A$2:$A$149) -> 88
A44: Concluída | B44: =COUNTIF('Lula 2022 (2023-2026)'!$H$2:$H$149,"Concluída") -> 14
A45: Em andamento | B45: =COUNTIF('Lula 2022 (2023-2026)'!$H$2:$H$149,"Em andamento") -> 24
A46: Não iniciada | B46: =COUNTIF('Lula 2022 (2023-2026)'!$H$2:$H$149,"Não iniciada") -> 1
A47: Sem dados (a pesquisar ou sem fonte) | B47: =COUNTIF('Lula 2022 (2023-2026)'!$H$2:$H$149,"Sem dados") -> 49
A48: % cumpridas entre as avaliadas (exclui Sem dados) | B48: =IF(B43-B47=0,0,B44/(B43-B47)) -> 0.35897436
